{
  "metrics": [
    {
      "id": "66c34b81b2a8beb7d162e859",
      "name": "learner0.test_accuracy"
    },
    {
      "id": "66c34b81b2a8beb7d162e85b",
      "name": "learner0.relative_rating"
    },
    {
      "id": "66c34b81b2a8beb7d162e85d",
      "name": "learner1.test_accuracy"
    },
    {
      "id": "66c34b81b2a8beb7d162e85f",
      "name": "learner1.relative_rating"
    },
    {
      "id": "66c34b81b2a8beb7d162e861",
      "name": "learner2.test_accuracy"
    },
    {
      "id": "66c34b81b2a8beb7d162e863",
      "name": "learner2.relative_rating"
    },
    {
      "id": "66c34b81b2a8beb7d162e865",
      "name": "learner3.test_accuracy"
    },
    {
      "id": "66c34b81b2a8beb7d162e867",
      "name": "learner3.relative_rating"
    },
    {
      "id": "66c34b81b2a8beb7d162e869",
      "name": "learner4.test_accuracy"
    },
    {
      "id": "66c34b81b2a8beb7d162e86b",
      "name": "learner4.relative_rating"
    },
    {
      "id": "66c34b81b2a8beb7d162e86d",
      "name": "learner5.test_accuracy"
    },
    {
      "id": "66c34b81b2a8beb7d162e86f",
      "name": "learner5.relative_rating"
    },
    {
      "id": "66c34b81b2a8beb7d162e871",
      "name": "learner6.test_accuracy"
    },
    {
      "id": "66c34b81b2a8beb7d162e873",
      "name": "learner6.relative_rating"
    },
    {
      "id": "66c34b81b2a8beb7d162e875",
      "name": "learner7.test_accuracy"
    },
    {
      "id": "66c34b81b2a8beb7d162e877",
      "name": "learner7.relative_rating"
    },
    {
      "id": "66c34b81b2a8beb7d162e879",
      "name": "learner8.test_accuracy"
    },
    {
      "id": "66c34b81b2a8beb7d162e87b",
      "name": "learner8.relative_rating"
    },
    {
      "id": "66c34b81b2a8beb7d162e87d",
      "name": "learner9.test_accuracy"
    },
    {
      "id": "66c34b81b2a8beb7d162e87f",
      "name": "learner9.relative_rating"
    },
    {
      "id": "66c34b81b2a8beb7d162e881",
      "name": "learner10.test_accuracy"
    },
    {
      "id": "66c34b81b2a8beb7d162e883",
      "name": "learner10.relative_rating"
    },
    {
      "id": "66c34b81b2a8beb7d162e885",
      "name": "learner11.test_accuracy"
    },
    {
      "id": "66c34b81b2a8beb7d162e887",
      "name": "learner11.relative_rating"
    },
    {
      "id": "66c34b81b2a8beb7d162e889",
      "name": "learner12.test_accuracy"
    },
    {
      "id": "66c34b81b2a8beb7d162e88b",
      "name": "learner12.relative_rating"
    },
    {
      "id": "66c34b81b2a8beb7d162e88d",
      "name": "learner13.test_accuracy"
    },
    {
      "id": "66c34b81b2a8beb7d162e88f",
      "name": "learner13.relative_rating"
    },
    {
      "id": "66c34b81b2a8beb7d162e891",
      "name": "learner14.test_accuracy"
    },
    {
      "id": "66c34b81b2a8beb7d162e893",
      "name": "learner14.relative_rating"
    },
    {
      "id": "66c34b81b2a8beb7d162e895",
      "name": "learner15.test_accuracy"
    },
    {
      "id": "66c34b81b2a8beb7d162e897",
      "name": "learner15.relative_rating"
    },
    {
      "id": "66c34b81b2a8beb7d162e899",
      "name": "learner16.test_accuracy"
    },
    {
      "id": "66c34b81b2a8beb7d162e89b",
      "name": "learner16.relative_rating"
    },
    {
      "id": "66c34b81b2a8beb7d162e89d",
      "name": "learner17.test_accuracy"
    },
    {
      "id": "66c34b81b2a8beb7d162e89f",
      "name": "learner17.relative_rating"
    },
    {
      "id": "66c34b81b2a8beb7d162e8a1",
      "name": "learner18.test_accuracy"
    },
    {
      "id": "66c34b81b2a8beb7d162e8a3",
      "name": "learner18.relative_rating"
    },
    {
      "id": "66c34b81b2a8beb7d162e8a5",
      "name": "learner19.test_accuracy"
    },
    {
      "id": "66c34b81b2a8beb7d162e8a7",
      "name": "learner19.relative_rating"
    },
    {
      "id": "66c34b81b2a8beb7d162e8a9",
      "name": "ensemble.best_rated_accuracy"
    },
    {
      "id": "66c34b81b2a8beb7d162e8ab",
      "name": "ensemble.majority_accuracy"
    }
  ]
}