{
  "test_accuracy": {
    "steps": [
      20,
      40,
      60,
      80,
      100,
      120,
      140,
      160,
      180,
      200,
      220,
      240,
      260,
      280,
      300,
      320,
      340,
      360,
      380,
      400,
      420,
      440,
      460,
      480,
      500,
      520,
      540,
      560,
      580,
      600
    ],
    "timestamps": [
      "2024-06-25T20:16:48.021823",
      "2024-06-25T20:16:48.022264",
      "2024-06-25T20:16:48.022704",
      "2024-06-25T20:16:48.023241",
      "2024-06-25T20:16:48.023707",
      "2024-06-25T20:16:48.024218",
      "2024-06-25T20:16:48.024735",
      "2024-06-25T20:16:48.025251",
      "2024-06-25T20:16:48.025735",
      "2024-06-25T20:16:48.026174",
      "2024-06-25T20:16:48.026665",
      "2024-06-25T20:16:48.027080",
      "2024-06-25T20:16:48.027547",
      "2024-06-25T20:16:48.027943",
      "2024-06-25T20:16:48.028421",
      "2024-06-25T20:16:48.028863",
      "2024-06-25T20:16:48.029323",
      "2024-06-25T20:16:48.029788",
      "2024-06-25T20:16:48.030248",
      "2024-06-25T20:16:48.030655",
      "2024-06-25T20:16:48.031279",
      "2024-06-25T20:16:48.031739",
      "2024-06-25T20:16:48.032206",
      "2024-06-25T20:16:48.032646",
      "2024-06-25T20:16:48.033044",
      "2024-06-25T20:16:48.033468",
      "2024-06-25T20:16:48.033922",
      "2024-06-25T20:16:48.034381",
      "2024-06-25T20:16:48.034873",
      "2024-06-25T20:16:48.035400"
    ],
    "values": [
      0.88,
      0.92,
      0.92,
      0.92,
      0.96,
      0.94,
      0.92,
      0.94,
      0.94,
      0.94,
      0.94,
      0.92,
      0.92,
      0.92,
      0.94,
      0.94,
      0.92,
      0.94,
      0.94,
      0.94,
      0.94,
      0.94,
      0.94,
      0.94,
      0.94,
      0.94,
      0.94,
      0.94,
      0.94,
      0.94
    ]
  },
  "train_correct": {
    "steps": [
      1,
      2,
      3,
      4,
      5,
      6,
      7,
      8,
      9,
      10,
      11,
      12,
      13,
      14,
      15,
      16,
      17,
      18,
      19,
      20,
      21,
      22,
      23,
      24,
      25,
      26,
      27,
      28,
      29,
      30,
      31,
      32,
      33,
      34,
      35,
      36,
      37,
      38,
      39,
      40,
      41,
      42,
      43,
      44,
      45,
      46,
      47,
      48,
      49,
      50,
      51,
      52,
      53,
      54,
      55,
      56,
      57,
      58,
      59,
      60,
      61,
      62,
      63,
      64,
      65,
      66,
      67,
      68,
      69,
      70,
      71,
      72,
      73,
      74,
      75,
      76,
      77,
      78,
      79,
      80,
      81,
      82,
      83,
      84,
      85,
      86,
      87,
      88,
      89,
      90,
      91,
      92,
      93,
      94,
      95,
      96,
      97,
      98,
      99,
      100,
      101,
      102,
      103,
      104,
      105,
      106,
      107,
      108,
      109,
      110,
      111,
      112,
      113,
      114,
      115,
      116,
      117,
      118,
      119,
      120,
      121,
      122,
      123,
      124,
      125,
      126,
      127,
      128,
      129,
      130,
      131,
      132,
      133,
      134,
      135,
      136,
      137,
      138,
      139,
      140,
      141,
      142,
      143,
      144,
      145,
      146,
      147,
      148,
      149,
      150,
      151,
      152,
      153,
      154,
      155,
      156,
      157,
      158,
      159,
      160,
      161,
      162,
      163,
      164,
      165,
      166,
      167,
      168,
      169,
      170,
      171,
      172,
      173,
      174,
      175,
      176,
      177,
      178,
      179,
      180,
      181,
      182,
      183,
      184,
      185,
      186,
      187,
      188,
      189,
      190,
      191,
      192,
      193,
      194,
      195,
      196,
      197,
      198,
      199,
      200,
      201,
      202,
      203,
      204,
      205,
      206,
      207,
      208,
      209,
      210,
      211,
      212,
      213,
      214,
      215,
      216,
      217,
      218,
      219,
      220,
      221,
      222,
      223,
      224,
      225,
      226,
      227,
      228,
      229,
      230,
      231,
      232,
      233,
      234,
      235,
      236,
      237,
      238,
      239,
      240,
      241,
      242,
      243,
      244,
      245,
      246,
      247,
      248,
      249,
      250,
      251,
      252,
      253,
      254,
      255,
      256,
      257,
      258,
      259,
      260,
      261,
      262,
      263,
      264,
      265,
      266,
      267,
      268,
      269,
      270,
      271,
      272,
      273,
      274,
      275,
      276,
      277,
      278,
      279,
      280,
      281,
      282,
      283,
      284,
      285,
      286,
      287,
      288,
      289,
      290,
      291,
      292,
      293,
      294,
      295,
      296,
      297,
      298,
      299,
      300,
      301,
      302,
      303,
      304,
      305,
      306,
      307,
      308,
      309,
      310,
      311,
      312,
      313,
      314,
      315,
      316,
      317,
      318,
      319,
      320,
      321,
      322,
      323,
      324,
      325,
      326,
      327,
      328,
      329,
      330,
      331,
      332,
      333,
      334,
      335,
      336,
      337,
      338,
      339,
      340,
      341,
      342,
      343,
      344,
      345,
      346,
      347,
      348,
      349,
      350,
      351,
      352,
      353,
      354,
      355,
      356,
      357,
      358,
      359,
      360,
      361,
      362,
      363,
      364,
      365,
      366,
      367,
      368,
      369,
      370,
      371,
      372,
      373,
      374,
      375,
      376,
      377,
      378,
      379,
      380,
      381,
      382,
      383,
      384,
      385,
      386,
      387,
      388,
      389,
      390,
      391,
      392,
      393,
      394,
      395,
      396,
      397,
      398,
      399,
      400,
      401,
      402,
      403,
      404,
      405,
      406,
      407,
      408,
      409,
      410,
      411,
      412,
      413,
      414,
      415,
      416,
      417,
      418,
      419,
      420,
      421,
      422,
      423,
      424,
      425,
      426,
      427,
      428,
      429,
      430,
      431,
      432,
      433,
      434,
      435,
      436,
      437,
      438,
      439,
      440,
      441,
      442,
      443,
      444,
      445,
      446,
      447,
      448,
      449,
      450,
      451,
      452,
      453,
      454,
      455,
      456,
      457,
      458,
      459,
      460,
      461,
      462,
      463,
      464,
      465,
      466,
      467,
      468,
      469,
      470,
      471,
      472,
      473,
      474,
      475,
      476,
      477,
      478,
      479,
      480,
      481,
      482,
      483,
      484,
      485,
      486,
      487,
      488,
      489,
      490,
      491,
      492,
      493,
      494,
      495,
      496,
      497,
      498,
      499,
      500,
      501,
      502,
      503,
      504,
      505,
      506,
      507,
      508,
      509,
      510,
      511,
      512,
      513,
      514,
      515,
      516,
      517,
      518,
      519,
      520,
      521,
      522,
      523,
      524,
      525,
      526,
      527,
      528,
      529,
      530,
      531,
      532,
      533,
      534,
      535,
      536,
      537,
      538,
      539,
      540,
      541,
      542,
      543,
      544,
      545,
      546,
      547,
      548,
      549,
      550,
      551,
      552,
      553,
      554,
      555,
      556,
      557,
      558,
      559,
      560,
      561,
      562,
      563,
      564,
      565,
      566,
      567,
      568,
      569,
      570,
      571,
      572,
      573,
      574,
      575,
      576,
      577,
      578,
      579,
      580,
      581,
      582,
      583,
      584,
      585,
      586,
      587,
      588,
      589,
      590,
      591,
      592,
      593,
      594,
      595,
      596,
      597,
      598,
      599,
      600
    ],
    "timestamps": [
      "2024-06-25T20:16:48.021280",
      "2024-06-25T20:16:48.021286",
      "2024-06-25T20:16:48.021363",
      "2024-06-25T20:16:48.021387",
      "2024-06-25T20:16:48.021392",
      "2024-06-25T20:16:48.021424",
      "2024-06-25T20:16:48.021446",
      "2024-06-25T20:16:48.021450",
      "2024-06-25T20:16:48.021469",
      "2024-06-25T20:16:48.021473",
      "2024-06-25T20:16:48.021477",
      "2024-06-25T20:16:48.021480",
      "2024-06-25T20:16:48.021501",
      "2024-06-25T20:16:48.021520",
      "2024-06-25T20:16:48.021523",
      "2024-06-25T20:16:48.021527",
      "2024-06-25T20:16:48.021545",
      "2024-06-25T20:16:48.021549",
      "2024-06-25T20:16:48.021553",
      "2024-06-25T20:16:48.021827",
      "2024-06-25T20:16:48.021831",
      "2024-06-25T20:16:48.021834",
      "2024-06-25T20:16:48.021853",
      "2024-06-25T20:16:48.021871",
      "2024-06-25T20:16:48.021874",
      "2024-06-25T20:16:48.021892",
      "2024-06-25T20:16:48.021896",
      "2024-06-25T20:16:48.021914",
      "2024-06-25T20:16:48.021918",
      "2024-06-25T20:16:48.021921",
      "2024-06-25T20:16:48.021925",
      "2024-06-25T20:16:48.021942",
      "2024-06-25T20:16:48.021946",
      "2024-06-25T20:16:48.021964",
      "2024-06-25T20:16:48.021982",
      "2024-06-25T20:16:48.021985",
      "2024-06-25T20:16:48.021989",
      "2024-06-25T20:16:48.021992",
      "2024-06-25T20:16:48.022010",
      "2024-06-25T20:16:48.022267",
      "2024-06-25T20:16:48.022271",
      "2024-06-25T20:16:48.022288",
      "2024-06-25T20:16:48.022292",
      "2024-06-25T20:16:48.022295",
      "2024-06-25T20:16:48.022299",
      "2024-06-25T20:16:48.022302",
      "2024-06-25T20:16:48.022305",
      "2024-06-25T20:16:48.022309",
      "2024-06-25T20:16:48.022313",
      "2024-06-25T20:16:48.022316",
      "2024-06-25T20:16:48.022333",
      "2024-06-25T20:16:48.022351",
      "2024-06-25T20:16:48.022368",
      "2024-06-25T20:16:48.022371",
      "2024-06-25T20:16:48.022375",
      "2024-06-25T20:16:48.022392",
      "2024-06-25T20:16:48.022409",
      "2024-06-25T20:16:48.022426",
      "2024-06-25T20:16:48.022443",
      "2024-06-25T20:16:48.022707",
      "2024-06-25T20:16:48.022725",
      "2024-06-25T20:16:48.022742",
      "2024-06-25T20:16:48.022746",
      "2024-06-25T20:16:48.022763",
      "2024-06-25T20:16:48.022780",
      "2024-06-25T20:16:48.022783",
      "2024-06-25T20:16:48.022787",
      "2024-06-25T20:16:48.022806",
      "2024-06-25T20:16:48.022823",
      "2024-06-25T20:16:48.022841",
      "2024-06-25T20:16:48.022844",
      "2024-06-25T20:16:48.022861",
      "2024-06-25T20:16:48.022865",
      "2024-06-25T20:16:48.022882",
      "2024-06-25T20:16:48.022899",
      "2024-06-25T20:16:48.022916",
      "2024-06-25T20:16:48.022933",
      "2024-06-25T20:16:48.022951",
      "2024-06-25T20:16:48.022968",
      "2024-06-25T20:16:48.023244",
      "2024-06-25T20:16:48.023262",
      "2024-06-25T20:16:48.023265",
      "2024-06-25T20:16:48.023283",
      "2024-06-25T20:16:48.023300",
      "2024-06-25T20:16:48.023303",
      "2024-06-25T20:16:48.023307",
      "2024-06-25T20:16:48.023310",
      "2024-06-25T20:16:48.023327",
      "2024-06-25T20:16:48.023345",
      "2024-06-25T20:16:48.023362",
      "2024-06-25T20:16:48.023379",
      "2024-06-25T20:16:48.023396",
      "2024-06-25T20:16:48.023400",
      "2024-06-25T20:16:48.023403",
      "2024-06-25T20:16:48.023407",
      "2024-06-25T20:16:48.023424",
      "2024-06-25T20:16:48.023428",
      "2024-06-25T20:16:48.023431",
      "2024-06-25T20:16:48.023434",
      "2024-06-25T20:16:48.023711",
      "2024-06-25T20:16:48.023714",
      "2024-06-25T20:16:48.023733",
      "2024-06-25T20:16:48.023737",
      "2024-06-25T20:16:48.023740",
      "2024-06-25T20:16:48.023744",
      "2024-06-25T20:16:48.023780",
      "2024-06-25T20:16:48.023783",
      "2024-06-25T20:16:48.023802",
      "2024-06-25T20:16:48.023821",
      "2024-06-25T20:16:48.023839",
      "2024-06-25T20:16:48.023843",
      "2024-06-25T20:16:48.023847",
      "2024-06-25T20:16:48.023850",
      "2024-06-25T20:16:48.023869",
      "2024-06-25T20:16:48.023887",
      "2024-06-25T20:16:48.023891",
      "2024-06-25T20:16:48.023910",
      "2024-06-25T20:16:48.023928",
      "2024-06-25T20:16:48.023932",
      "2024-06-25T20:16:48.024222",
      "2024-06-25T20:16:48.024225",
      "2024-06-25T20:16:48.024243",
      "2024-06-25T20:16:48.024251",
      "2024-06-25T20:16:48.024269",
      "2024-06-25T20:16:48.024272",
      "2024-06-25T20:16:48.024290",
      "2024-06-25T20:16:48.024319",
      "2024-06-25T20:16:48.024336",
      "2024-06-25T20:16:48.024340",
      "2024-06-25T20:16:48.024357",
      "2024-06-25T20:16:48.024361",
      "2024-06-25T20:16:48.024378",
      "2024-06-25T20:16:48.024395",
      "2024-06-25T20:16:48.024413",
      "2024-06-25T20:16:48.024416",
      "2024-06-25T20:16:48.024434",
      "2024-06-25T20:16:48.024451",
      "2024-06-25T20:16:48.024483",
      "2024-06-25T20:16:48.024486",
      "2024-06-25T20:16:48.024738",
      "2024-06-25T20:16:48.024742",
      "2024-06-25T20:16:48.024746",
      "2024-06-25T20:16:48.024763",
      "2024-06-25T20:16:48.024780",
      "2024-06-25T20:16:48.024798",
      "2024-06-25T20:16:48.024801",
      "2024-06-25T20:16:48.024818",
      "2024-06-25T20:16:48.024836",
      "2024-06-25T20:16:48.024840",
      "2024-06-25T20:16:48.024857",
      "2024-06-25T20:16:48.024874",
      "2024-06-25T20:16:48.024877",
      "2024-06-25T20:16:48.024894",
      "2024-06-25T20:16:48.024898",
      "2024-06-25T20:16:48.024915",
      "2024-06-25T20:16:48.024932",
      "2024-06-25T20:16:48.024949",
      "2024-06-25T20:16:48.024966",
      "2024-06-25T20:16:48.024983",
      "2024-06-25T20:16:48.025254",
      "2024-06-25T20:16:48.025272",
      "2024-06-25T20:16:48.025290",
      "2024-06-25T20:16:48.025302",
      "2024-06-25T20:16:48.025305",
      "2024-06-25T20:16:48.025324",
      "2024-06-25T20:16:48.025328",
      "2024-06-25T20:16:48.025345",
      "2024-06-25T20:16:48.025363",
      "2024-06-25T20:16:48.025380",
      "2024-06-25T20:16:48.025398",
      "2024-06-25T20:16:48.025402",
      "2024-06-25T20:16:48.025419",
      "2024-06-25T20:16:48.025423",
      "2024-06-25T20:16:48.025440",
      "2024-06-25T20:16:48.025444",
      "2024-06-25T20:16:48.025447",
      "2024-06-25T20:16:48.025464",
      "2024-06-25T20:16:48.025481",
      "2024-06-25T20:16:48.025490",
      "2024-06-25T20:16:48.025739",
      "2024-06-25T20:16:48.025742",
      "2024-06-25T20:16:48.025746",
      "2024-06-25T20:16:48.025749",
      "2024-06-25T20:16:48.025767",
      "2024-06-25T20:16:48.025784",
      "2024-06-25T20:16:48.025787",
      "2024-06-25T20:16:48.025791",
      "2024-06-25T20:16:48.025808",
      "2024-06-25T20:16:48.025812",
      "2024-06-25T20:16:48.025815",
      "2024-06-25T20:16:48.025818",
      "2024-06-25T20:16:48.025835",
      "2024-06-25T20:16:48.025853",
      "2024-06-25T20:16:48.025870",
      "2024-06-25T20:16:48.025887",
      "2024-06-25T20:16:48.025890",
      "2024-06-25T20:16:48.025908",
      "2024-06-25T20:16:48.025925",
      "2024-06-25T20:16:48.025928",
      "2024-06-25T20:16:48.026178",
      "2024-06-25T20:16:48.026195",
      "2024-06-25T20:16:48.026198",
      "2024-06-25T20:16:48.026216",
      "2024-06-25T20:16:48.026233",
      "2024-06-25T20:16:48.026250",
      "2024-06-25T20:16:48.026267",
      "2024-06-25T20:16:48.026271",
      "2024-06-25T20:16:48.026274",
      "2024-06-25T20:16:48.026291",
      "2024-06-25T20:16:48.026295",
      "2024-06-25T20:16:48.026298",
      "2024-06-25T20:16:48.026315",
      "2024-06-25T20:16:48.026332",
      "2024-06-25T20:16:48.026336",
      "2024-06-25T20:16:48.026353",
      "2024-06-25T20:16:48.026370",
      "2024-06-25T20:16:48.026387",
      "2024-06-25T20:16:48.026404",
      "2024-06-25T20:16:48.026408",
      "2024-06-25T20:16:48.026669",
      "2024-06-25T20:16:48.026672",
      "2024-06-25T20:16:48.026690",
      "2024-06-25T20:16:48.026694",
      "2024-06-25T20:16:48.026697",
      "2024-06-25T20:16:48.026701",
      "2024-06-25T20:16:48.026718",
      "2024-06-25T20:16:48.026736",
      "2024-06-25T20:16:48.026739",
      "2024-06-25T20:16:48.026743",
      "2024-06-25T20:16:48.026746",
      "2024-06-25T20:16:48.026749",
      "2024-06-25T20:16:48.026753",
      "2024-06-25T20:16:48.026770",
      "2024-06-25T20:16:48.026789",
      "2024-06-25T20:16:48.026792",
      "2024-06-25T20:16:48.026810",
      "2024-06-25T20:16:48.026813",
      "2024-06-25T20:16:48.026817",
      "2024-06-25T20:16:48.026835",
      "2024-06-25T20:16:48.027084",
      "2024-06-25T20:16:48.027101",
      "2024-06-25T20:16:48.027104",
      "2024-06-25T20:16:48.027122",
      "2024-06-25T20:16:48.027139",
      "2024-06-25T20:16:48.027142",
      "2024-06-25T20:16:48.027146",
      "2024-06-25T20:16:48.027149",
      "2024-06-25T20:16:48.027166",
      "2024-06-25T20:16:48.027184",
      "2024-06-25T20:16:48.027201",
      "2024-06-25T20:16:48.027204",
      "2024-06-25T20:16:48.027208",
      "2024-06-25T20:16:48.027225",
      "2024-06-25T20:16:48.027228",
      "2024-06-25T20:16:48.027232",
      "2024-06-25T20:16:48.027249",
      "2024-06-25T20:16:48.027254",
      "2024-06-25T20:16:48.027271",
      "2024-06-25T20:16:48.027289",
      "2024-06-25T20:16:48.027551",
      "2024-06-25T20:16:48.027555",
      "2024-06-25T20:16:48.027567",
      "2024-06-25T20:16:48.027584",
      "2024-06-25T20:16:48.027588",
      "2024-06-25T20:16:48.027591",
      "2024-06-25T20:16:48.027595",
      "2024-06-25T20:16:48.027598",
      "2024-06-25T20:16:48.027602",
      "2024-06-25T20:16:48.027619",
      "2024-06-25T20:16:48.027623",
      "2024-06-25T20:16:48.027626",
      "2024-06-25T20:16:48.027629",
      "2024-06-25T20:16:48.027633",
      "2024-06-25T20:16:48.027636",
      "2024-06-25T20:16:48.027639",
      "2024-06-25T20:16:48.027657",
      "2024-06-25T20:16:48.027674",
      "2024-06-25T20:16:48.027678",
      "2024-06-25T20:16:48.027695",
      "2024-06-25T20:16:48.027947",
      "2024-06-25T20:16:48.027964",
      "2024-06-25T20:16:48.027981",
      "2024-06-25T20:16:48.027998",
      "2024-06-25T20:16:48.028015",
      "2024-06-25T20:16:48.028032",
      "2024-06-25T20:16:48.028036",
      "2024-06-25T20:16:48.028039",
      "2024-06-25T20:16:48.028043",
      "2024-06-25T20:16:48.028065",
      "2024-06-25T20:16:48.028068",
      "2024-06-25T20:16:48.028071",
      "2024-06-25T20:16:48.028075",
      "2024-06-25T20:16:48.028092",
      "2024-06-25T20:16:48.028109",
      "2024-06-25T20:16:48.028127",
      "2024-06-25T20:16:48.028130",
      "2024-06-25T20:16:48.028133",
      "2024-06-25T20:16:48.028151",
      "2024-06-25T20:16:48.028154",
      "2024-06-25T20:16:48.028426",
      "2024-06-25T20:16:48.028431",
      "2024-06-25T20:16:48.028455",
      "2024-06-25T20:16:48.028459",
      "2024-06-25T20:16:48.028476",
      "2024-06-25T20:16:48.028479",
      "2024-06-25T20:16:48.028496",
      "2024-06-25T20:16:48.028499",
      "2024-06-25T20:16:48.028516",
      "2024-06-25T20:16:48.028519",
      "2024-06-25T20:16:48.028522",
      "2024-06-25T20:16:48.028539",
      "2024-06-25T20:16:48.028542",
      "2024-06-25T20:16:48.028559",
      "2024-06-25T20:16:48.028576",
      "2024-06-25T20:16:48.028584",
      "2024-06-25T20:16:48.028587",
      "2024-06-25T20:16:48.028604",
      "2024-06-25T20:16:48.028621",
      "2024-06-25T20:16:48.028624",
      "2024-06-25T20:16:48.028866",
      "2024-06-25T20:16:48.028870",
      "2024-06-25T20:16:48.028873",
      "2024-06-25T20:16:48.028890",
      "2024-06-25T20:16:48.028907",
      "2024-06-25T20:16:48.028924",
      "2024-06-25T20:16:48.028927",
      "2024-06-25T20:16:48.028944",
      "2024-06-25T20:16:48.028960",
      "2024-06-25T20:16:48.028964",
      "2024-06-25T20:16:48.028980",
      "2024-06-25T20:16:48.028984",
      "2024-06-25T20:16:48.029008",
      "2024-06-25T20:16:48.029029",
      "2024-06-25T20:16:48.029034",
      "2024-06-25T20:16:48.029038",
      "2024-06-25T20:16:48.029061",
      "2024-06-25T20:16:48.029064",
      "2024-06-25T20:16:48.029081",
      "2024-06-25T20:16:48.029085",
      "2024-06-25T20:16:48.029326",
      "2024-06-25T20:16:48.029343",
      "2024-06-25T20:16:48.029360",
      "2024-06-25T20:16:48.029363",
      "2024-06-25T20:16:48.029405",
      "2024-06-25T20:16:48.029422",
      "2024-06-25T20:16:48.029439",
      "2024-06-25T20:16:48.029442",
      "2024-06-25T20:16:48.029445",
      "2024-06-25T20:16:48.029449",
      "2024-06-25T20:16:48.029452",
      "2024-06-25T20:16:48.029469",
      "2024-06-25T20:16:48.029472",
      "2024-06-25T20:16:48.029490",
      "2024-06-25T20:16:48.029506",
      "2024-06-25T20:16:48.029510",
      "2024-06-25T20:16:48.029513",
      "2024-06-25T20:16:48.029530",
      "2024-06-25T20:16:48.029533",
      "2024-06-25T20:16:48.029536",
      "2024-06-25T20:16:48.029803",
      "2024-06-25T20:16:48.029806",
      "2024-06-25T20:16:48.029823",
      "2024-06-25T20:16:48.029845",
      "2024-06-25T20:16:48.029864",
      "2024-06-25T20:16:48.029868",
      "2024-06-25T20:16:48.029889",
      "2024-06-25T20:16:48.029893",
      "2024-06-25T20:16:48.029917",
      "2024-06-25T20:16:48.029922",
      "2024-06-25T20:16:48.029926",
      "2024-06-25T20:16:48.029929",
      "2024-06-25T20:16:48.029946",
      "2024-06-25T20:16:48.029949",
      "2024-06-25T20:16:48.029966",
      "2024-06-25T20:16:48.029969",
      "2024-06-25T20:16:48.029986",
      "2024-06-25T20:16:48.029989",
      "2024-06-25T20:16:48.029993",
      "2024-06-25T20:16:48.030009",
      "2024-06-25T20:16:48.030251",
      "2024-06-25T20:16:48.030255",
      "2024-06-25T20:16:48.030258",
      "2024-06-25T20:16:48.030275",
      "2024-06-25T20:16:48.030292",
      "2024-06-25T20:16:48.030295",
      "2024-06-25T20:16:48.030312",
      "2024-06-25T20:16:48.030331",
      "2024-06-25T20:16:48.030334",
      "2024-06-25T20:16:48.030338",
      "2024-06-25T20:16:48.030341",
      "2024-06-25T20:16:48.030358",
      "2024-06-25T20:16:48.030375",
      "2024-06-25T20:16:48.030392",
      "2024-06-25T20:16:48.030395",
      "2024-06-25T20:16:48.030399",
      "2024-06-25T20:16:48.030402",
      "2024-06-25T20:16:48.030406",
      "2024-06-25T20:16:48.030409",
      "2024-06-25T20:16:48.030412",
      "2024-06-25T20:16:48.030659",
      "2024-06-25T20:16:48.030676",
      "2024-06-25T20:16:48.030680",
      "2024-06-25T20:16:48.030683",
      "2024-06-25T20:16:48.030704",
      "2024-06-25T20:16:48.030709",
      "2024-06-25T20:16:48.030727",
      "2024-06-25T20:16:48.030731",
      "2024-06-25T20:16:48.030734",
      "2024-06-25T20:16:48.030738",
      "2024-06-25T20:16:48.030937",
      "2024-06-25T20:16:48.030940",
      "2024-06-25T20:16:48.030961",
      "2024-06-25T20:16:48.030964",
      "2024-06-25T20:16:48.030982",
      "2024-06-25T20:16:48.030986",
      "2024-06-25T20:16:48.030989",
      "2024-06-25T20:16:48.031006",
      "2024-06-25T20:16:48.031010",
      "2024-06-25T20:16:48.031027",
      "2024-06-25T20:16:48.031283",
      "2024-06-25T20:16:48.031300",
      "2024-06-25T20:16:48.031304",
      "2024-06-25T20:16:48.031340",
      "2024-06-25T20:16:48.031344",
      "2024-06-25T20:16:48.031347",
      "2024-06-25T20:16:48.031364",
      "2024-06-25T20:16:48.031381",
      "2024-06-25T20:16:48.031384",
      "2024-06-25T20:16:48.031388",
      "2024-06-25T20:16:48.031405",
      "2024-06-25T20:16:48.031421",
      "2024-06-25T20:16:48.031438",
      "2024-06-25T20:16:48.031441",
      "2024-06-25T20:16:48.031445",
      "2024-06-25T20:16:48.031461",
      "2024-06-25T20:16:48.031465",
      "2024-06-25T20:16:48.031468",
      "2024-06-25T20:16:48.031485",
      "2024-06-25T20:16:48.031502",
      "2024-06-25T20:16:48.031742",
      "2024-06-25T20:16:48.031760",
      "2024-06-25T20:16:48.031763",
      "2024-06-25T20:16:48.031789",
      "2024-06-25T20:16:48.031793",
      "2024-06-25T20:16:48.031796",
      "2024-06-25T20:16:48.031799",
      "2024-06-25T20:16:48.031803",
      "2024-06-25T20:16:48.031806",
      "2024-06-25T20:16:48.031825",
      "2024-06-25T20:16:48.031842",
      "2024-06-25T20:16:48.031845",
      "2024-06-25T20:16:48.031863",
      "2024-06-25T20:16:48.031879",
      "2024-06-25T20:16:48.031897",
      "2024-06-25T20:16:48.031925",
      "2024-06-25T20:16:48.031942",
      "2024-06-25T20:16:48.031945",
      "2024-06-25T20:16:48.031962",
      "2024-06-25T20:16:48.031965",
      "2024-06-25T20:16:48.032209",
      "2024-06-25T20:16:48.032226",
      "2024-06-25T20:16:48.032229",
      "2024-06-25T20:16:48.032233",
      "2024-06-25T20:16:48.032250",
      "2024-06-25T20:16:48.032267",
      "2024-06-25T20:16:48.032270",
      "2024-06-25T20:16:48.032273",
      "2024-06-25T20:16:48.032291",
      "2024-06-25T20:16:48.032307",
      "2024-06-25T20:16:48.032311",
      "2024-06-25T20:16:48.032328",
      "2024-06-25T20:16:48.032331",
      "2024-06-25T20:16:48.032347",
      "2024-06-25T20:16:48.032351",
      "2024-06-25T20:16:48.032368",
      "2024-06-25T20:16:48.032371",
      "2024-06-25T20:16:48.032375",
      "2024-06-25T20:16:48.032392",
      "2024-06-25T20:16:48.032408",
      "2024-06-25T20:16:48.032649",
      "2024-06-25T20:16:48.032653",
      "2024-06-25T20:16:48.032661",
      "2024-06-25T20:16:48.032678",
      "2024-06-25T20:16:48.032695",
      "2024-06-25T20:16:48.032699",
      "2024-06-25T20:16:48.032715",
      "2024-06-25T20:16:48.032732",
      "2024-06-25T20:16:48.032735",
      "2024-06-25T20:16:48.032752",
      "2024-06-25T20:16:48.032756",
      "2024-06-25T20:16:48.032759",
      "2024-06-25T20:16:48.032762",
      "2024-06-25T20:16:48.032779",
      "2024-06-25T20:16:48.032782",
      "2024-06-25T20:16:48.032792",
      "2024-06-25T20:16:48.032796",
      "2024-06-25T20:16:48.032799",
      "2024-06-25T20:16:48.032802",
      "2024-06-25T20:16:48.032806",
      "2024-06-25T20:16:48.033048",
      "2024-06-25T20:16:48.033051",
      "2024-06-25T20:16:48.033068",
      "2024-06-25T20:16:48.033071",
      "2024-06-25T20:16:48.033096",
      "2024-06-25T20:16:48.033113",
      "2024-06-25T20:16:48.033129",
      "2024-06-25T20:16:48.033133",
      "2024-06-25T20:16:48.033136",
      "2024-06-25T20:16:48.033153",
      "2024-06-25T20:16:48.033156",
      "2024-06-25T20:16:48.033178",
      "2024-06-25T20:16:48.033195",
      "2024-06-25T20:16:48.033212",
      "2024-06-25T20:16:48.033215",
      "2024-06-25T20:16:48.033219",
      "2024-06-25T20:16:48.033222",
      "2024-06-25T20:16:48.033225",
      "2024-06-25T20:16:48.033228",
      "2024-06-25T20:16:48.033232",
      "2024-06-25T20:16:48.033472",
      "2024-06-25T20:16:48.033489",
      "2024-06-25T20:16:48.033505",
      "2024-06-25T20:16:48.033509",
      "2024-06-25T20:16:48.033526",
      "2024-06-25T20:16:48.033542",
      "2024-06-25T20:16:48.033546",
      "2024-06-25T20:16:48.033549",
      "2024-06-25T20:16:48.033567",
      "2024-06-25T20:16:48.033570",
      "2024-06-25T20:16:48.033587",
      "2024-06-25T20:16:48.033590",
      "2024-06-25T20:16:48.033607",
      "2024-06-25T20:16:48.033624",
      "2024-06-25T20:16:48.033627",
      "2024-06-25T20:16:48.033644",
      "2024-06-25T20:16:48.033647",
      "2024-06-25T20:16:48.033664",
      "2024-06-25T20:16:48.033668",
      "2024-06-25T20:16:48.033671",
      "2024-06-25T20:16:48.033925",
      "2024-06-25T20:16:48.033929",
      "2024-06-25T20:16:48.033946",
      "2024-06-25T20:16:48.033963",
      "2024-06-25T20:16:48.033979",
      "2024-06-25T20:16:48.033997",
      "2024-06-25T20:16:48.034000",
      "2024-06-25T20:16:48.034004",
      "2024-06-25T20:16:48.034020",
      "2024-06-25T20:16:48.034037",
      "2024-06-25T20:16:48.034054",
      "2024-06-25T20:16:48.034057",
      "2024-06-25T20:16:48.034061",
      "2024-06-25T20:16:48.034064",
      "2024-06-25T20:16:48.034067",
      "2024-06-25T20:16:48.034071",
      "2024-06-25T20:16:48.034074",
      "2024-06-25T20:16:48.034091",
      "2024-06-25T20:16:48.034107",
      "2024-06-25T20:16:48.034124",
      "2024-06-25T20:16:48.034384",
      "2024-06-25T20:16:48.034401",
      "2024-06-25T20:16:48.034419",
      "2024-06-25T20:16:48.034424",
      "2024-06-25T20:16:48.034428",
      "2024-06-25T20:16:48.034449",
      "2024-06-25T20:16:48.034474",
      "2024-06-25T20:16:48.034478",
      "2024-06-25T20:16:48.034483",
      "2024-06-25T20:16:48.034507",
      "2024-06-25T20:16:48.034525",
      "2024-06-25T20:16:48.034542",
      "2024-06-25T20:16:48.034545",
      "2024-06-25T20:16:48.034549",
      "2024-06-25T20:16:48.034552",
      "2024-06-25T20:16:48.034569",
      "2024-06-25T20:16:48.034572",
      "2024-06-25T20:16:48.034589",
      "2024-06-25T20:16:48.034605",
      "2024-06-25T20:16:48.034622",
      "2024-06-25T20:16:48.034877",
      "2024-06-25T20:16:48.034894",
      "2024-06-25T20:16:48.034911",
      "2024-06-25T20:16:48.034914",
      "2024-06-25T20:16:48.034931",
      "2024-06-25T20:16:48.034947",
      "2024-06-25T20:16:48.034964",
      "2024-06-25T20:16:48.034967",
      "2024-06-25T20:16:48.034984",
      "2024-06-25T20:16:48.035001",
      "2024-06-25T20:16:48.035018",
      "2024-06-25T20:16:48.035021",
      "2024-06-25T20:16:48.035038",
      "2024-06-25T20:16:48.035054",
      "2024-06-25T20:16:48.035071",
      "2024-06-25T20:16:48.035082",
      "2024-06-25T20:16:48.035099",
      "2024-06-25T20:16:48.035116",
      "2024-06-25T20:16:48.035132",
      "2024-06-25T20:16:48.035149",
      "2024-06-25T20:16:48.035403"
    ],
    "values": [
      0,
      0,
      0,
      1,
      1,
      1,
      1,
      1,
      2,
      2,
      2,
      2,
      3,
      4,
      4,
      4,
      5,
      5,
      5,
      6,
      6,
      6,
      7,
      8,
      8,
      9,
      9,
      10,
      10,
      10,
      10,
      11,
      11,
      12,
      12,
      12,
      12,
      12,
      13,
      13,
      13,
      14,
      14,
      14,
      14,
      14,
      14,
      14,
      14,
      14,
      15,
      16,
      17,
      17,
      17,
      18,
      19,
      20,
      20,
      21,
      22,
      23,
      23,
      24,
      25,
      25,
      25,
      26,
      27,
      27,
      27,
      28,
      28,
      29,
      30,
      31,
      32,
      33,
      34,
      34,
      35,
      35,
      36,
      37,
      37,
      37,
      37,
      38,
      39,
      40,
      40,
      41,
      41,
      41,
      41,
      42,
      42,
      42,
      42,
      42,
      42,
      43,
      43,
      43,
      43,
      44,
      44,
      45,
      46,
      47,
      47,
      47,
      47,
      48,
      49,
      49,
      50,
      51,
      51,
      52,
      52,
      53,
      53,
      54,
      54,
      55,
      56,
      57,
      57,
      58,
      58,
      59,
      60,
      61,
      61,
      62,
      63,
      64,
      64,
      64,
      64,
      64,
      65,
      66,
      67,
      67,
      68,
      69,
      69,
      70,
      70,
      70,
      71,
      71,
      72,
      72,
      72,
      73,
      73,
      74,
      75,
      76,
      76,
      76,
      77,
      77,
      78,
      79,
      80,
      81,
      81,
      82,
      82,
      83,
      83,
      83,
      83,
      84,
      84,
      84,
      84,
      84,
      84,
      85,
      86,
      86,
      86,
      87,
      87,
      87,
      87,
      88,
      89,
      90,
      91,
      91,
      92,
      93,
      93,
      93,
      94,
      94,
      95,
      96,
      97,
      98,
      98,
      98,
      99,
      99,
      99,
      100,
      101,
      101,
      102,
      103,
      104,
      105,
      105,
      105,
      105,
      106,
      106,
      106,
      106,
      107,
      108,
      108,
      108,
      108,
      108,
      108,
      109,
      110,
      110,
      111,
      111,
      111,
      112,
      112,
      113,
      113,
      114,
      115,
      115,
      115,
      115,
      116,
      117,
      118,
      118,
      118,
      119,
      119,
      119,
      120,
      120,
      121,
      122,
      122,
      122,
      122,
      123,
      123,
      123,
      123,
      123,
      123,
      124,
      124,
      124,
      124,
      124,
      124,
      124,
      125,
      126,
      126,
      127,
      127,
      127,
      128,
      129,
      129,
      130,
      130,
      130,
      130,
      131,
      131,
      131,
      131,
      131,
      132,
      133,
      133,
      133,
      134,
      134,
      134,
      134,
      134,
      134,
      135,
      135,
      136,
      136,
      137,
      137,
      137,
      138,
      138,
      139,
      139,
      139,
      139,
      140,
      141,
      141,
      141,
      141,
      141,
      142,
      143,
      144,
      144,
      145,
      146,
      146,
      147,
      147,
      148,
      149,
      149,
      149,
      150,
      150,
      151,
      151,
      151,
      152,
      153,
      153,
      154,
      155,
      156,
      156,
      156,
      156,
      156,
      157,
      157,
      158,
      159,
      159,
      159,
      160,
      160,
      160,
      161,
      161,
      162,
      163,
      164,
      164,
      165,
      165,
      166,
      166,
      166,
      166,
      167,
      167,
      168,
      168,
      169,
      169,
      169,
      169,
      169,
      169,
      169,
      170,
      171,
      171,
      172,
      173,
      173,
      173,
      173,
      174,
      175,
      176,
      176,
      176,
      176,
      176,
      176,
      176,
      176,
      177,
      177,
      177,
      177,
      177,
      178,
      178,
      178,
      178,
      179,
      179,
      179,
      179,
      180,
      180,
      180,
      181,
      181,
      182,
      183,
      184,
      184,
      184,
      184,
      184,
      185,
      186,
      186,
      186,
      187,
      188,
      189,
      189,
      189,
      190,
      190,
      190,
      191,
      191,
      191,
      192,
      192,
      192,
      192,
      192,
      192,
      192,
      192,
      193,
      194,
      194,
      195,
      196,
      197,
      198,
      199,
      199,
      200,
      200,
      200,
      201,
      201,
      201,
      202,
      203,
      203,
      203,
      204,
      205,
      205,
      206,
      206,
      206,
      206,
      207,
      207,
      207,
      208,
      209,
      209,
      209,
      209,
      210,
      211,
      211,
      212,
      213,
      213,
      214,
      214,
      214,
      214,
      215,
      215,
      215,
      215,
      215,
      215,
      215,
      215,
      215,
      216,
      216,
      217,
      218,
      219,
      219,
      219,
      220,
      220,
      221,
      222,
      223,
      223,
      223,
      223,
      223,
      223,
      223,
      223,
      224,
      224,
      224,
      225,
      226,
      226,
      226,
      227,
      227,
      227,
      227,
      228,
      229,
      229,
      230,
      230,
      231,
      231,
      231,
      232,
      232,
      233,
      234,
      235,
      236,
      236,
      236,
      237,
      238,
      239,
      239,
      239,
      239,
      239,
      239,
      239,
      240,
      241,
      242,
      242,
      243,
      244,
      244,
      244,
      245,
      246,
      246,
      246,
      247,
      248,
      249,
      249,
      249,
      249,
      250,
      250,
      251,
      252,
      253,
      254,
      255,
      256,
      256,
      257,
      258,
      259,
      259,
      260,
      261,
      262,
      262,
      263,
      264,
      265,
      265,
      266,
      267,
      268,
      269,
      270
    ]
  },
  "train_observed": {
    "steps": [
      1,
      2,
      3,
      4,
      5,
      6,
      7,
      8,
      9,
      10,
      11,
      12,
      13,
      14,
      15,
      16,
      17,
      18,
      19,
      20,
      21,
      22,
      23,
      24,
      25,
      26,
      27,
      28,
      29,
      30,
      31,
      32,
      33,
      34,
      35,
      36,
      37,
      38,
      39,
      40,
      41,
      42,
      43,
      44,
      45,
      46,
      47,
      48,
      49,
      50,
      51,
      52,
      53,
      54,
      55,
      56,
      57,
      58,
      59,
      60,
      61,
      62,
      63,
      64,
      65,
      66,
      67,
      68,
      69,
      70,
      71,
      72,
      73,
      74,
      75,
      76,
      77,
      78,
      79,
      80,
      81,
      82,
      83,
      84,
      85,
      86,
      87,
      88,
      89,
      90,
      91,
      92,
      93,
      94,
      95,
      96,
      97,
      98,
      99,
      100,
      101,
      102,
      103,
      104,
      105,
      106,
      107,
      108,
      109,
      110,
      111,
      112,
      113,
      114,
      115,
      116,
      117,
      118,
      119,
      120,
      121,
      122,
      123,
      124,
      125,
      126,
      127,
      128,
      129,
      130,
      131,
      132,
      133,
      134,
      135,
      136,
      137,
      138,
      139,
      140,
      141,
      142,
      143,
      144,
      145,
      146,
      147,
      148,
      149,
      150,
      151,
      152,
      153,
      154,
      155,
      156,
      157,
      158,
      159,
      160,
      161,
      162,
      163,
      164,
      165,
      166,
      167,
      168,
      169,
      170,
      171,
      172,
      173,
      174,
      175,
      176,
      177,
      178,
      179,
      180,
      181,
      182,
      183,
      184,
      185,
      186,
      187,
      188,
      189,
      190,
      191,
      192,
      193,
      194,
      195,
      196,
      197,
      198,
      199,
      200,
      201,
      202,
      203,
      204,
      205,
      206,
      207,
      208,
      209,
      210,
      211,
      212,
      213,
      214,
      215,
      216,
      217,
      218,
      219,
      220,
      221,
      222,
      223,
      224,
      225,
      226,
      227,
      228,
      229,
      230,
      231,
      232,
      233,
      234,
      235,
      236,
      237,
      238,
      239,
      240,
      241,
      242,
      243,
      244,
      245,
      246,
      247,
      248,
      249,
      250,
      251,
      252,
      253,
      254,
      255,
      256,
      257,
      258,
      259,
      260,
      261,
      262,
      263,
      264,
      265,
      266,
      267,
      268,
      269,
      270,
      271,
      272,
      273,
      274,
      275,
      276,
      277,
      278,
      279,
      280,
      281,
      282,
      283,
      284,
      285,
      286,
      287,
      288,
      289,
      290,
      291,
      292,
      293,
      294,
      295,
      296,
      297,
      298,
      299,
      300,
      301,
      302,
      303,
      304,
      305,
      306,
      307,
      308,
      309,
      310,
      311,
      312,
      313,
      314,
      315,
      316,
      317,
      318,
      319,
      320,
      321,
      322,
      323,
      324,
      325,
      326,
      327,
      328,
      329,
      330,
      331,
      332,
      333,
      334,
      335,
      336,
      337,
      338,
      339,
      340,
      341,
      342,
      343,
      344,
      345,
      346,
      347,
      348,
      349,
      350,
      351,
      352,
      353,
      354,
      355,
      356,
      357,
      358,
      359,
      360,
      361,
      362,
      363,
      364,
      365,
      366,
      367,
      368,
      369,
      370,
      371,
      372,
      373,
      374,
      375,
      376,
      377,
      378,
      379,
      380,
      381,
      382,
      383,
      384,
      385,
      386,
      387,
      388,
      389,
      390,
      391,
      392,
      393,
      394,
      395,
      396,
      397,
      398,
      399,
      400,
      401,
      402,
      403,
      404,
      405,
      406,
      407,
      408,
      409,
      410,
      411,
      412,
      413,
      414,
      415,
      416,
      417,
      418,
      419,
      420,
      421,
      422,
      423,
      424,
      425,
      426,
      427,
      428,
      429,
      430,
      431,
      432,
      433,
      434,
      435,
      436,
      437,
      438,
      439,
      440,
      441,
      442,
      443,
      444,
      445,
      446,
      447,
      448,
      449,
      450,
      451,
      452,
      453,
      454,
      455,
      456,
      457,
      458,
      459,
      460,
      461,
      462,
      463,
      464,
      465,
      466,
      467,
      468,
      469,
      470,
      471,
      472,
      473,
      474,
      475,
      476,
      477,
      478,
      479,
      480,
      481,
      482,
      483,
      484,
      485,
      486,
      487,
      488,
      489,
      490,
      491,
      492,
      493,
      494,
      495,
      496,
      497,
      498,
      499,
      500,
      501,
      502,
      503,
      504,
      505,
      506,
      507,
      508,
      509,
      510,
      511,
      512,
      513,
      514,
      515,
      516,
      517,
      518,
      519,
      520,
      521,
      522,
      523,
      524,
      525,
      526,
      527,
      528,
      529,
      530,
      531,
      532,
      533,
      534,
      535,
      536,
      537,
      538,
      539,
      540,
      541,
      542,
      543,
      544,
      545,
      546,
      547,
      548,
      549,
      550,
      551,
      552,
      553,
      554,
      555,
      556,
      557,
      558,
      559,
      560,
      561,
      562,
      563,
      564,
      565,
      566,
      567,
      568,
      569,
      570,
      571,
      572,
      573,
      574,
      575,
      576,
      577,
      578,
      579,
      580,
      581,
      582,
      583,
      584,
      585,
      586,
      587,
      588,
      589,
      590,
      591,
      592,
      593,
      594,
      595,
      596,
      597,
      598,
      599,
      600
    ],
    "timestamps": [
      "2024-06-25T20:16:48.021271",
      "2024-06-25T20:16:48.021284",
      "2024-06-25T20:16:48.021360",
      "2024-06-25T20:16:48.021385",
      "2024-06-25T20:16:48.021390",
      "2024-06-25T20:16:48.021422",
      "2024-06-25T20:16:48.021444",
      "2024-06-25T20:16:48.021448",
      "2024-06-25T20:16:48.021467",
      "2024-06-25T20:16:48.021471",
      "2024-06-25T20:16:48.021475",
      "2024-06-25T20:16:48.021478",
      "2024-06-25T20:16:48.021499",
      "2024-06-25T20:16:48.021518",
      "2024-06-25T20:16:48.021522",
      "2024-06-25T20:16:48.021525",
      "2024-06-25T20:16:48.021543",
      "2024-06-25T20:16:48.021547",
      "2024-06-25T20:16:48.021551",
      "2024-06-25T20:16:48.021826",
      "2024-06-25T20:16:48.021829",
      "2024-06-25T20:16:48.021833",
      "2024-06-25T20:16:48.021851",
      "2024-06-25T20:16:48.021869",
      "2024-06-25T20:16:48.021873",
      "2024-06-25T20:16:48.021891",
      "2024-06-25T20:16:48.021894",
      "2024-06-25T20:16:48.021912",
      "2024-06-25T20:16:48.021916",
      "2024-06-25T20:16:48.021919",
      "2024-06-25T20:16:48.021923",
      "2024-06-25T20:16:48.021941",
      "2024-06-25T20:16:48.021944",
      "2024-06-25T20:16:48.021962",
      "2024-06-25T20:16:48.021980",
      "2024-06-25T20:16:48.021983",
      "2024-06-25T20:16:48.021987",
      "2024-06-25T20:16:48.021990",
      "2024-06-25T20:16:48.022008",
      "2024-06-25T20:16:48.022266",
      "2024-06-25T20:16:48.022269",
      "2024-06-25T20:16:48.022287",
      "2024-06-25T20:16:48.022290",
      "2024-06-25T20:16:48.022294",
      "2024-06-25T20:16:48.022297",
      "2024-06-25T20:16:48.022300",
      "2024-06-25T20:16:48.022304",
      "2024-06-25T20:16:48.022307",
      "2024-06-25T20:16:48.022311",
      "2024-06-25T20:16:48.022314",
      "2024-06-25T20:16:48.022332",
      "2024-06-25T20:16:48.022349",
      "2024-06-25T20:16:48.022366",
      "2024-06-25T20:16:48.022370",
      "2024-06-25T20:16:48.022373",
      "2024-06-25T20:16:48.022390",
      "2024-06-25T20:16:48.022407",
      "2024-06-25T20:16:48.022425",
      "2024-06-25T20:16:48.022442",
      "2024-06-25T20:16:48.022705",
      "2024-06-25T20:16:48.022723",
      "2024-06-25T20:16:48.022740",
      "2024-06-25T20:16:48.022744",
      "2024-06-25T20:16:48.022761",
      "2024-06-25T20:16:48.022778",
      "2024-06-25T20:16:48.022782",
      "2024-06-25T20:16:48.022785",
      "2024-06-25T20:16:48.022804",
      "2024-06-25T20:16:48.022822",
      "2024-06-25T20:16:48.022839",
      "2024-06-25T20:16:48.022842",
      "2024-06-25T20:16:48.022859",
      "2024-06-25T20:16:48.022863",
      "2024-06-25T20:16:48.022880",
      "2024-06-25T20:16:48.022897",
      "2024-06-25T20:16:48.022914",
      "2024-06-25T20:16:48.022932",
      "2024-06-25T20:16:48.022949",
      "2024-06-25T20:16:48.022967",
      "2024-06-25T20:16:48.023242",
      "2024-06-25T20:16:48.023260",
      "2024-06-25T20:16:48.023263",
      "2024-06-25T20:16:48.023281",
      "2024-06-25T20:16:48.023298",
      "2024-06-25T20:16:48.023302",
      "2024-06-25T20:16:48.023305",
      "2024-06-25T20:16:48.023309",
      "2024-06-25T20:16:48.023326",
      "2024-06-25T20:16:48.023343",
      "2024-06-25T20:16:48.023360",
      "2024-06-25T20:16:48.023377",
      "2024-06-25T20:16:48.023395",
      "2024-06-25T20:16:48.023398",
      "2024-06-25T20:16:48.023402",
      "2024-06-25T20:16:48.023405",
      "2024-06-25T20:16:48.023422",
      "2024-06-25T20:16:48.023426",
      "2024-06-25T20:16:48.023429",
      "2024-06-25T20:16:48.023433",
      "2024-06-25T20:16:48.023709",
      "2024-06-25T20:16:48.023713",
      "2024-06-25T20:16:48.023731",
      "2024-06-25T20:16:48.023735",
      "2024-06-25T20:16:48.023739",
      "2024-06-25T20:16:48.023742",
      "2024-06-25T20:16:48.023778",
      "2024-06-25T20:16:48.023782",
      "2024-06-25T20:16:48.023800",
      "2024-06-25T20:16:48.023819",
      "2024-06-25T20:16:48.023837",
      "2024-06-25T20:16:48.023841",
      "2024-06-25T20:16:48.023845",
      "2024-06-25T20:16:48.023849",
      "2024-06-25T20:16:48.023867",
      "2024-06-25T20:16:48.023885",
      "2024-06-25T20:16:48.023889",
      "2024-06-25T20:16:48.023908",
      "2024-06-25T20:16:48.023926",
      "2024-06-25T20:16:48.023930",
      "2024-06-25T20:16:48.024220",
      "2024-06-25T20:16:48.024224",
      "2024-06-25T20:16:48.024241",
      "2024-06-25T20:16:48.024249",
      "2024-06-25T20:16:48.024267",
      "2024-06-25T20:16:48.024270",
      "2024-06-25T20:16:48.024288",
      "2024-06-25T20:16:48.024317",
      "2024-06-25T20:16:48.024335",
      "2024-06-25T20:16:48.024338",
      "2024-06-25T20:16:48.024356",
      "2024-06-25T20:16:48.024359",
      "2024-06-25T20:16:48.024376",
      "2024-06-25T20:16:48.024394",
      "2024-06-25T20:16:48.024411",
      "2024-06-25T20:16:48.024415",
      "2024-06-25T20:16:48.024432",
      "2024-06-25T20:16:48.024449",
      "2024-06-25T20:16:48.024481",
      "2024-06-25T20:16:48.024485",
      "2024-06-25T20:16:48.024736",
      "2024-06-25T20:16:48.024740",
      "2024-06-25T20:16:48.024744",
      "2024-06-25T20:16:48.024762",
      "2024-06-25T20:16:48.024779",
      "2024-06-25T20:16:48.024796",
      "2024-06-25T20:16:48.024799",
      "2024-06-25T20:16:48.024816",
      "2024-06-25T20:16:48.024834",
      "2024-06-25T20:16:48.024838",
      "2024-06-25T20:16:48.024855",
      "2024-06-25T20:16:48.024872",
      "2024-06-25T20:16:48.024876",
      "2024-06-25T20:16:48.024893",
      "2024-06-25T20:16:48.024896",
      "2024-06-25T20:16:48.024913",
      "2024-06-25T20:16:48.024930",
      "2024-06-25T20:16:48.024947",
      "2024-06-25T20:16:48.024965",
      "2024-06-25T20:16:48.024982",
      "2024-06-25T20:16:48.025253",
      "2024-06-25T20:16:48.025270",
      "2024-06-25T20:16:48.025288",
      "2024-06-25T20:16:48.025300",
      "2024-06-25T20:16:48.025303",
      "2024-06-25T20:16:48.025322",
      "2024-06-25T20:16:48.025326",
      "2024-06-25T20:16:48.025343",
      "2024-06-25T20:16:48.025361",
      "2024-06-25T20:16:48.025379",
      "2024-06-25T20:16:48.025396",
      "2024-06-25T20:16:48.025400",
      "2024-06-25T20:16:48.025417",
      "2024-06-25T20:16:48.025421",
      "2024-06-25T20:16:48.025439",
      "2024-06-25T20:16:48.025442",
      "2024-06-25T20:16:48.025445",
      "2024-06-25T20:16:48.025463",
      "2024-06-25T20:16:48.025480",
      "2024-06-25T20:16:48.025488",
      "2024-06-25T20:16:48.025737",
      "2024-06-25T20:16:48.025741",
      "2024-06-25T20:16:48.025744",
      "2024-06-25T20:16:48.025747",
      "2024-06-25T20:16:48.025765",
      "2024-06-25T20:16:48.025782",
      "2024-06-25T20:16:48.025786",
      "2024-06-25T20:16:48.025789",
      "2024-06-25T20:16:48.025806",
      "2024-06-25T20:16:48.025810",
      "2024-06-25T20:16:48.025813",
      "2024-06-25T20:16:48.025817",
      "2024-06-25T20:16:48.025834",
      "2024-06-25T20:16:48.025851",
      "2024-06-25T20:16:48.025868",
      "2024-06-25T20:16:48.025885",
      "2024-06-25T20:16:48.025889",
      "2024-06-25T20:16:48.025906",
      "2024-06-25T20:16:48.025923",
      "2024-06-25T20:16:48.025927",
      "2024-06-25T20:16:48.026176",
      "2024-06-25T20:16:48.026193",
      "2024-06-25T20:16:48.026197",
      "2024-06-25T20:16:48.026214",
      "2024-06-25T20:16:48.026231",
      "2024-06-25T20:16:48.026248",
      "2024-06-25T20:16:48.026265",
      "2024-06-25T20:16:48.026269",
      "2024-06-25T20:16:48.026272",
      "2024-06-25T20:16:48.026290",
      "2024-06-25T20:16:48.026293",
      "2024-06-25T20:16:48.026296",
      "2024-06-25T20:16:48.026313",
      "2024-06-25T20:16:48.026330",
      "2024-06-25T20:16:48.026334",
      "2024-06-25T20:16:48.026351",
      "2024-06-25T20:16:48.026368",
      "2024-06-25T20:16:48.026386",
      "2024-06-25T20:16:48.026403",
      "2024-06-25T20:16:48.026406",
      "2024-06-25T20:16:48.026667",
      "2024-06-25T20:16:48.026671",
      "2024-06-25T20:16:48.026689",
      "2024-06-25T20:16:48.026692",
      "2024-06-25T20:16:48.026696",
      "2024-06-25T20:16:48.026699",
      "2024-06-25T20:16:48.026716",
      "2024-06-25T20:16:48.026734",
      "2024-06-25T20:16:48.026737",
      "2024-06-25T20:16:48.026741",
      "2024-06-25T20:16:48.026744",
      "2024-06-25T20:16:48.026748",
      "2024-06-25T20:16:48.026751",
      "2024-06-25T20:16:48.026768",
      "2024-06-25T20:16:48.026787",
      "2024-06-25T20:16:48.026791",
      "2024-06-25T20:16:48.026808",
      "2024-06-25T20:16:48.026812",
      "2024-06-25T20:16:48.026815",
      "2024-06-25T20:16:48.026833",
      "2024-06-25T20:16:48.027082",
      "2024-06-25T20:16:48.027099",
      "2024-06-25T20:16:48.027103",
      "2024-06-25T20:16:48.027120",
      "2024-06-25T20:16:48.027137",
      "2024-06-25T20:16:48.027141",
      "2024-06-25T20:16:48.027144",
      "2024-06-25T20:16:48.027148",
      "2024-06-25T20:16:48.027165",
      "2024-06-25T20:16:48.027182",
      "2024-06-25T20:16:48.027199",
      "2024-06-25T20:16:48.027203",
      "2024-06-25T20:16:48.027206",
      "2024-06-25T20:16:48.027223",
      "2024-06-25T20:16:48.027227",
      "2024-06-25T20:16:48.027231",
      "2024-06-25T20:16:48.027248",
      "2024-06-25T20:16:48.027252",
      "2024-06-25T20:16:48.027270",
      "2024-06-25T20:16:48.027287",
      "2024-06-25T20:16:48.027549",
      "2024-06-25T20:16:48.027553",
      "2024-06-25T20:16:48.027565",
      "2024-06-25T20:16:48.027583",
      "2024-06-25T20:16:48.027586",
      "2024-06-25T20:16:48.027590",
      "2024-06-25T20:16:48.027593",
      "2024-06-25T20:16:48.027597",
      "2024-06-25T20:16:48.027600",
      "2024-06-25T20:16:48.027617",
      "2024-06-25T20:16:48.027621",
      "2024-06-25T20:16:48.027624",
      "2024-06-25T20:16:48.027628",
      "2024-06-25T20:16:48.027631",
      "2024-06-25T20:16:48.027634",
      "2024-06-25T20:16:48.027638",
      "2024-06-25T20:16:48.027655",
      "2024-06-25T20:16:48.027672",
      "2024-06-25T20:16:48.027676",
      "2024-06-25T20:16:48.027693",
      "2024-06-25T20:16:48.027945",
      "2024-06-25T20:16:48.027962",
      "2024-06-25T20:16:48.027979",
      "2024-06-25T20:16:48.027996",
      "2024-06-25T20:16:48.028013",
      "2024-06-25T20:16:48.028031",
      "2024-06-25T20:16:48.028034",
      "2024-06-25T20:16:48.028038",
      "2024-06-25T20:16:48.028041",
      "2024-06-25T20:16:48.028063",
      "2024-06-25T20:16:48.028066",
      "2024-06-25T20:16:48.028070",
      "2024-06-25T20:16:48.028073",
      "2024-06-25T20:16:48.028090",
      "2024-06-25T20:16:48.028108",
      "2024-06-25T20:16:48.028125",
      "2024-06-25T20:16:48.028128",
      "2024-06-25T20:16:48.028132",
      "2024-06-25T20:16:48.028149",
      "2024-06-25T20:16:48.028153",
      "2024-06-25T20:16:48.028424",
      "2024-06-25T20:16:48.028428",
      "2024-06-25T20:16:48.028453",
      "2024-06-25T20:16:48.028458",
      "2024-06-25T20:16:48.028474",
      "2024-06-25T20:16:48.028478",
      "2024-06-25T20:16:48.028494",
      "2024-06-25T20:16:48.028498",
      "2024-06-25T20:16:48.028514",
      "2024-06-25T20:16:48.028517",
      "2024-06-25T20:16:48.028521",
      "2024-06-25T20:16:48.028537",
      "2024-06-25T20:16:48.028541",
      "2024-06-25T20:16:48.028557",
      "2024-06-25T20:16:48.028574",
      "2024-06-25T20:16:48.028578",
      "2024-06-25T20:16:48.028586",
      "2024-06-25T20:16:48.028603",
      "2024-06-25T20:16:48.028619",
      "2024-06-25T20:16:48.028623",
      "2024-06-25T20:16:48.028865",
      "2024-06-25T20:16:48.028868",
      "2024-06-25T20:16:48.028871",
      "2024-06-25T20:16:48.028888",
      "2024-06-25T20:16:48.028905",
      "2024-06-25T20:16:48.028922",
      "2024-06-25T20:16:48.028925",
      "2024-06-25T20:16:48.028942",
      "2024-06-25T20:16:48.028959",
      "2024-06-25T20:16:48.028962",
      "2024-06-25T20:16:48.028979",
      "2024-06-25T20:16:48.028982",
      "2024-06-25T20:16:48.029006",
      "2024-06-25T20:16:48.029027",
      "2024-06-25T20:16:48.029031",
      "2024-06-25T20:16:48.029036",
      "2024-06-25T20:16:48.029059",
      "2024-06-25T20:16:48.029063",
      "2024-06-25T20:16:48.029080",
      "2024-06-25T20:16:48.029083",
      "2024-06-25T20:16:48.029325",
      "2024-06-25T20:16:48.029342",
      "2024-06-25T20:16:48.029358",
      "2024-06-25T20:16:48.029362",
      "2024-06-25T20:16:48.029403",
      "2024-06-25T20:16:48.029420",
      "2024-06-25T20:16:48.029437",
      "2024-06-25T20:16:48.029440",
      "2024-06-25T20:16:48.029444",
      "2024-06-25T20:16:48.029447",
      "2024-06-25T20:16:48.029450",
      "2024-06-25T20:16:48.029467",
      "2024-06-25T20:16:48.029470",
      "2024-06-25T20:16:48.029488",
      "2024-06-25T20:16:48.029505",
      "2024-06-25T20:16:48.029508",
      "2024-06-25T20:16:48.029511",
      "2024-06-25T20:16:48.029528",
      "2024-06-25T20:16:48.029532",
      "2024-06-25T20:16:48.029535",
      "2024-06-25T20:16:48.029790",
      "2024-06-25T20:16:48.029804",
      "2024-06-25T20:16:48.029821",
      "2024-06-25T20:16:48.029842",
      "2024-06-25T20:16:48.029863",
      "2024-06-25T20:16:48.029866",
      "2024-06-25T20:16:48.029886",
      "2024-06-25T20:16:48.029891",
      "2024-06-25T20:16:48.029915",
      "2024-06-25T20:16:48.029920",
      "2024-06-25T20:16:48.029924",
      "2024-06-25T20:16:48.029928",
      "2024-06-25T20:16:48.029944",
      "2024-06-25T20:16:48.029948",
      "2024-06-25T20:16:48.029964",
      "2024-06-25T20:16:48.029968",
      "2024-06-25T20:16:48.029984",
      "2024-06-25T20:16:48.029988",
      "2024-06-25T20:16:48.029991",
      "2024-06-25T20:16:48.030008",
      "2024-06-25T20:16:48.030250",
      "2024-06-25T20:16:48.030253",
      "2024-06-25T20:16:48.030256",
      "2024-06-25T20:16:48.030273",
      "2024-06-25T20:16:48.030290",
      "2024-06-25T20:16:48.030294",
      "2024-06-25T20:16:48.030310",
      "2024-06-25T20:16:48.030329",
      "2024-06-25T20:16:48.030333",
      "2024-06-25T20:16:48.030336",
      "2024-06-25T20:16:48.030339",
      "2024-06-25T20:16:48.030357",
      "2024-06-25T20:16:48.030373",
      "2024-06-25T20:16:48.030390",
      "2024-06-25T20:16:48.030394",
      "2024-06-25T20:16:48.030397",
      "2024-06-25T20:16:48.030401",
      "2024-06-25T20:16:48.030404",
      "2024-06-25T20:16:48.030407",
      "2024-06-25T20:16:48.030411",
      "2024-06-25T20:16:48.030657",
      "2024-06-25T20:16:48.030675",
      "2024-06-25T20:16:48.030678",
      "2024-06-25T20:16:48.030681",
      "2024-06-25T20:16:48.030702",
      "2024-06-25T20:16:48.030707",
      "2024-06-25T20:16:48.030726",
      "2024-06-25T20:16:48.030729",
      "2024-06-25T20:16:48.030733",
      "2024-06-25T20:16:48.030736",
      "2024-06-25T20:16:48.030934",
      "2024-06-25T20:16:48.030939",
      "2024-06-25T20:16:48.030959",
      "2024-06-25T20:16:48.030963",
      "2024-06-25T20:16:48.030981",
      "2024-06-25T20:16:48.030984",
      "2024-06-25T20:16:48.030987",
      "2024-06-25T20:16:48.031005",
      "2024-06-25T20:16:48.031008",
      "2024-06-25T20:16:48.031025",
      "2024-06-25T20:16:48.031281",
      "2024-06-25T20:16:48.031298",
      "2024-06-25T20:16:48.031302",
      "2024-06-25T20:16:48.031338",
      "2024-06-25T20:16:48.031342",
      "2024-06-25T20:16:48.031345",
      "2024-06-25T20:16:48.031362",
      "2024-06-25T20:16:48.031379",
      "2024-06-25T20:16:48.031383",
      "2024-06-25T20:16:48.031386",
      "2024-06-25T20:16:48.031403",
      "2024-06-25T20:16:48.031419",
      "2024-06-25T20:16:48.031436",
      "2024-06-25T20:16:48.031440",
      "2024-06-25T20:16:48.031443",
      "2024-06-25T20:16:48.031460",
      "2024-06-25T20:16:48.031463",
      "2024-06-25T20:16:48.031466",
      "2024-06-25T20:16:48.031483",
      "2024-06-25T20:16:48.031500",
      "2024-06-25T20:16:48.031741",
      "2024-06-25T20:16:48.031758",
      "2024-06-25T20:16:48.031762",
      "2024-06-25T20:16:48.031787",
      "2024-06-25T20:16:48.031791",
      "2024-06-25T20:16:48.031794",
      "2024-06-25T20:16:48.031798",
      "2024-06-25T20:16:48.031801",
      "2024-06-25T20:16:48.031804",
      "2024-06-25T20:16:48.031823",
      "2024-06-25T20:16:48.031840",
      "2024-06-25T20:16:48.031844",
      "2024-06-25T20:16:48.031861",
      "2024-06-25T20:16:48.031878",
      "2024-06-25T20:16:48.031895",
      "2024-06-25T20:16:48.031912",
      "2024-06-25T20:16:48.031940",
      "2024-06-25T20:16:48.031944",
      "2024-06-25T20:16:48.031960",
      "2024-06-25T20:16:48.031964",
      "2024-06-25T20:16:48.032208",
      "2024-06-25T20:16:48.032224",
      "2024-06-25T20:16:48.032228",
      "2024-06-25T20:16:48.032231",
      "2024-06-25T20:16:48.032248",
      "2024-06-25T20:16:48.032265",
      "2024-06-25T20:16:48.032268",
      "2024-06-25T20:16:48.032272",
      "2024-06-25T20:16:48.032289",
      "2024-06-25T20:16:48.032306",
      "2024-06-25T20:16:48.032309",
      "2024-06-25T20:16:48.032326",
      "2024-06-25T20:16:48.032329",
      "2024-06-25T20:16:48.032346",
      "2024-06-25T20:16:48.032349",
      "2024-06-25T20:16:48.032366",
      "2024-06-25T20:16:48.032370",
      "2024-06-25T20:16:48.032373",
      "2024-06-25T20:16:48.032390",
      "2024-06-25T20:16:48.032407",
      "2024-06-25T20:16:48.032648",
      "2024-06-25T20:16:48.032651",
      "2024-06-25T20:16:48.032660",
      "2024-06-25T20:16:48.032677",
      "2024-06-25T20:16:48.032693",
      "2024-06-25T20:16:48.032697",
      "2024-06-25T20:16:48.032714",
      "2024-06-25T20:16:48.032730",
      "2024-06-25T20:16:48.032734",
      "2024-06-25T20:16:48.032751",
      "2024-06-25T20:16:48.032754",
      "2024-06-25T20:16:48.032757",
      "2024-06-25T20:16:48.032761",
      "2024-06-25T20:16:48.032777",
      "2024-06-25T20:16:48.032781",
      "2024-06-25T20:16:48.032784",
      "2024-06-25T20:16:48.032794",
      "2024-06-25T20:16:48.032798",
      "2024-06-25T20:16:48.032801",
      "2024-06-25T20:16:48.032804",
      "2024-06-25T20:16:48.033046",
      "2024-06-25T20:16:48.033049",
      "2024-06-25T20:16:48.033066",
      "2024-06-25T20:16:48.033069",
      "2024-06-25T20:16:48.033094",
      "2024-06-25T20:16:48.033111",
      "2024-06-25T20:16:48.033128",
      "2024-06-25T20:16:48.033131",
      "2024-06-25T20:16:48.033134",
      "2024-06-25T20:16:48.033151",
      "2024-06-25T20:16:48.033154",
      "2024-06-25T20:16:48.033176",
      "2024-06-25T20:16:48.033193",
      "2024-06-25T20:16:48.033210",
      "2024-06-25T20:16:48.033214",
      "2024-06-25T20:16:48.033217",
      "2024-06-25T20:16:48.033220",
      "2024-06-25T20:16:48.033224",
      "2024-06-25T20:16:48.033227",
      "2024-06-25T20:16:48.033230",
      "2024-06-25T20:16:48.033470",
      "2024-06-25T20:16:48.033487",
      "2024-06-25T20:16:48.033504",
      "2024-06-25T20:16:48.033507",
      "2024-06-25T20:16:48.033524",
      "2024-06-25T20:16:48.033541",
      "2024-06-25T20:16:48.033544",
      "2024-06-25T20:16:48.033548",
      "2024-06-25T20:16:48.033565",
      "2024-06-25T20:16:48.033569",
      "2024-06-25T20:16:48.033585",
      "2024-06-25T20:16:48.033589",
      "2024-06-25T20:16:48.033605",
      "2024-06-25T20:16:48.033622",
      "2024-06-25T20:16:48.033625",
      "2024-06-25T20:16:48.033642",
      "2024-06-25T20:16:48.033646",
      "2024-06-25T20:16:48.033663",
      "2024-06-25T20:16:48.033666",
      "2024-06-25T20:16:48.033669",
      "2024-06-25T20:16:48.033924",
      "2024-06-25T20:16:48.033927",
      "2024-06-25T20:16:48.033944",
      "2024-06-25T20:16:48.033961",
      "2024-06-25T20:16:48.033978",
      "2024-06-25T20:16:48.033995",
      "2024-06-25T20:16:48.033999",
      "2024-06-25T20:16:48.034002",
      "2024-06-25T20:16:48.034019",
      "2024-06-25T20:16:48.034035",
      "2024-06-25T20:16:48.034052",
      "2024-06-25T20:16:48.034056",
      "2024-06-25T20:16:48.034059",
      "2024-06-25T20:16:48.034062",
      "2024-06-25T20:16:48.034066",
      "2024-06-25T20:16:48.034069",
      "2024-06-25T20:16:48.034072",
      "2024-06-25T20:16:48.034089",
      "2024-06-25T20:16:48.034106",
      "2024-06-25T20:16:48.034122",
      "2024-06-25T20:16:48.034383",
      "2024-06-25T20:16:48.034400",
      "2024-06-25T20:16:48.034417",
      "2024-06-25T20:16:48.034422",
      "2024-06-25T20:16:48.034426",
      "2024-06-25T20:16:48.034447",
      "2024-06-25T20:16:48.034471",
      "2024-06-25T20:16:48.034476",
      "2024-06-25T20:16:48.034481",
      "2024-06-25T20:16:48.034505",
      "2024-06-25T20:16:48.034523",
      "2024-06-25T20:16:48.034540",
      "2024-06-25T20:16:48.034543",
      "2024-06-25T20:16:48.034547",
      "2024-06-25T20:16:48.034550",
      "2024-06-25T20:16:48.034567",
      "2024-06-25T20:16:48.034570",
      "2024-06-25T20:16:48.034587",
      "2024-06-25T20:16:48.034604",
      "2024-06-25T20:16:48.034620",
      "2024-06-25T20:16:48.034875",
      "2024-06-25T20:16:48.034892",
      "2024-06-25T20:16:48.034909",
      "2024-06-25T20:16:48.034912",
      "2024-06-25T20:16:48.034929",
      "2024-06-25T20:16:48.034946",
      "2024-06-25T20:16:48.034962",
      "2024-06-25T20:16:48.034966",
      "2024-06-25T20:16:48.034983",
      "2024-06-25T20:16:48.034999",
      "2024-06-25T20:16:48.035016",
      "2024-06-25T20:16:48.035020",
      "2024-06-25T20:16:48.035036",
      "2024-06-25T20:16:48.035053",
      "2024-06-25T20:16:48.035069",
      "2024-06-25T20:16:48.035073",
      "2024-06-25T20:16:48.035097",
      "2024-06-25T20:16:48.035114",
      "2024-06-25T20:16:48.035131",
      "2024-06-25T20:16:48.035147",
      "2024-06-25T20:16:48.035401"
    ],
    "values": [
      1,
      2,
      3,
      4,
      5,
      6,
      7,
      8,
      9,
      10,
      11,
      12,
      13,
      14,
      15,
      16,
      17,
      18,
      19,
      20,
      21,
      22,
      23,
      24,
      25,
      26,
      27,
      28,
      29,
      30,
      31,
      32,
      33,
      34,
      35,
      36,
      37,
      38,
      39,
      40,
      41,
      42,
      43,
      44,
      45,
      46,
      47,
      48,
      49,
      50,
      51,
      52,
      53,
      54,
      55,
      56,
      57,
      58,
      59,
      60,
      61,
      62,
      63,
      64,
      65,
      66,
      67,
      68,
      69,
      70,
      71,
      72,
      73,
      74,
      75,
      76,
      77,
      78,
      79,
      80,
      81,
      82,
      83,
      84,
      85,
      86,
      87,
      88,
      89,
      90,
      91,
      92,
      93,
      94,
      95,
      96,
      97,
      98,
      99,
      100,
      101,
      102,
      103,
      104,
      105,
      106,
      107,
      108,
      109,
      110,
      111,
      112,
      113,
      114,
      115,
      116,
      117,
      118,
      119,
      120,
      121,
      122,
      123,
      124,
      125,
      126,
      127,
      128,
      129,
      130,
      131,
      132,
      133,
      134,
      135,
      136,
      137,
      138,
      139,
      140,
      141,
      142,
      143,
      144,
      145,
      146,
      147,
      148,
      149,
      150,
      151,
      152,
      153,
      154,
      155,
      156,
      157,
      158,
      159,
      160,
      161,
      162,
      163,
      164,
      165,
      166,
      167,
      168,
      169,
      170,
      171,
      172,
      173,
      174,
      175,
      176,
      177,
      178,
      179,
      180,
      181,
      182,
      183,
      184,
      185,
      186,
      187,
      188,
      189,
      190,
      191,
      192,
      193,
      194,
      195,
      196,
      197,
      198,
      199,
      200,
      201,
      202,
      203,
      204,
      205,
      206,
      207,
      208,
      209,
      210,
      211,
      212,
      213,
      214,
      215,
      216,
      217,
      218,
      219,
      220,
      221,
      222,
      223,
      224,
      225,
      226,
      227,
      228,
      229,
      230,
      231,
      232,
      233,
      234,
      235,
      236,
      237,
      238,
      239,
      240,
      241,
      242,
      243,
      244,
      245,
      246,
      247,
      248,
      249,
      250,
      251,
      252,
      253,
      254,
      255,
      256,
      257,
      258,
      259,
      260,
      261,
      262,
      263,
      264,
      265,
      266,
      267,
      268,
      269,
      270,
      271,
      272,
      273,
      274,
      275,
      276,
      277,
      278,
      279,
      280,
      281,
      282,
      283,
      284,
      285,
      286,
      287,
      288,
      289,
      290,
      291,
      292,
      293,
      294,
      295,
      296,
      297,
      298,
      299,
      300,
      301,
      302,
      303,
      304,
      305,
      306,
      307,
      308,
      309,
      310,
      311,
      312,
      313,
      314,
      315,
      316,
      317,
      318,
      319,
      320,
      321,
      322,
      323,
      324,
      325,
      326,
      327,
      328,
      329,
      330,
      331,
      332,
      333,
      334,
      335,
      336,
      337,
      338,
      339,
      340,
      341,
      342,
      343,
      344,
      345,
      346,
      347,
      348,
      349,
      350,
      351,
      352,
      353,
      354,
      355,
      356,
      357,
      358,
      359,
      360,
      361,
      362,
      363,
      364,
      365,
      366,
      367,
      368,
      369,
      370,
      371,
      372,
      373,
      374,
      375,
      376,
      377,
      378,
      379,
      380,
      381,
      382,
      383,
      384,
      385,
      386,
      387,
      388,
      389,
      390,
      391,
      392,
      393,
      394,
      395,
      396,
      397,
      398,
      399,
      400,
      401,
      402,
      403,
      404,
      405,
      406,
      407,
      408,
      409,
      410,
      411,
      412,
      413,
      414,
      415,
      416,
      417,
      418,
      419,
      420,
      421,
      422,
      423,
      424,
      425,
      426,
      427,
      428,
      429,
      430,
      431,
      432,
      433,
      434,
      435,
      436,
      437,
      438,
      439,
      440,
      441,
      442,
      443,
      444,
      445,
      446,
      447,
      448,
      449,
      450,
      451,
      452,
      453,
      454,
      455,
      456,
      457,
      458,
      459,
      460,
      461,
      462,
      463,
      464,
      465,
      466,
      467,
      468,
      469,
      470,
      471,
      472,
      473,
      474,
      475,
      476,
      477,
      478,
      479,
      480,
      481,
      482,
      483,
      484,
      485,
      486,
      487,
      488,
      489,
      490,
      491,
      492,
      493,
      494,
      495,
      496,
      497,
      498,
      499,
      500,
      501,
      502,
      503,
      504,
      505,
      506,
      507,
      508,
      509,
      510,
      511,
      512,
      513,
      514,
      515,
      516,
      517,
      518,
      519,
      520,
      521,
      522,
      523,
      524,
      525,
      526,
      527,
      528,
      529,
      530,
      531,
      532,
      533,
      534,
      535,
      536,
      537,
      538,
      539,
      540,
      541,
      542,
      543,
      544,
      545,
      546,
      547,
      548,
      549,
      550,
      551,
      552,
      553,
      554,
      555,
      556,
      557,
      558,
      559,
      560,
      561,
      562,
      563,
      564,
      565,
      566,
      567,
      568,
      569,
      570,
      571,
      572,
      573,
      574,
      575,
      576,
      577,
      578,
      579,
      580,
      581,
      582,
      583,
      584,
      585,
      586,
      587,
      588,
      589,
      590,
      591,
      592,
      593,
      594,
      595,
      596,
      597,
      598,
      599,
      600
    ]
  }
}