{
  "metrics": [
    {
      "id": "6709a521c85f062399d3e0bd",
      "name": "learner4.train_correct"
    },
    {
      "id": "6709a521c85f062399d3e0bf",
      "name": "learner4.train_observed"
    },
    {
      "id": "6709a521c85f062399d3e0c1",
      "name": "learner4.games_played"
    },
    {
      "id": "6709a521c85f062399d3e0c3",
      "name": "learner4.games_won"
    },
    {
      "id": "6709a521c85f062399d3e0c5",
      "name": "learner4.games_lost"
    },
    {
      "id": "6709a521c85f062399d3e0c7",
      "name": "learner4.games_tie"
    },
    {
      "id": "6709a521c85f062399d3e0c9",
      "name": "learner4.rating"
    },
    {
      "id": "6709a521c85f062399d3e0cb",
      "name": "learner5.train_correct"
    },
    {
      "id": "6709a521c85f062399d3e0cd",
      "name": "learner5.train_observed"
    },
    {
      "id": "6709a521c85f062399d3e0cf",
      "name": "learner5.games_played"
    },
    {
      "id": "6709a521c85f062399d3e0d1",
      "name": "learner5.games_won"
    },
    {
      "id": "6709a521c85f062399d3e0d3",
      "name": "learner5.games_lost"
    },
    {
      "id": "6709a521c85f062399d3e0d5",
      "name": "learner5.games_tie"
    },
    {
      "id": "6709a521c85f062399d3e0d7",
      "name": "learner5.rating"
    },
    {
      "id": "6709a521c85f062399d3e0d9",
      "name": "learner3.train_correct"
    },
    {
      "id": "6709a521c85f062399d3e0db",
      "name": "learner3.train_observed"
    },
    {
      "id": "6709a521c85f062399d3e0dd",
      "name": "learner3.games_played"
    },
    {
      "id": "6709a521c85f062399d3e0df",
      "name": "learner3.games_won"
    },
    {
      "id": "6709a521c85f062399d3e0e1",
      "name": "learner3.games_lost"
    },
    {
      "id": "6709a521c85f062399d3e0e3",
      "name": "learner3.games_tie"
    },
    {
      "id": "6709a521c85f062399d3e0e5",
      "name": "learner3.rating"
    },
    {
      "id": "6709a521c85f062399d3e0e7",
      "name": "learner2.train_correct"
    },
    {
      "id": "6709a521c85f062399d3e0e9",
      "name": "learner2.train_observed"
    },
    {
      "id": "6709a521c85f062399d3e0eb",
      "name": "learner2.games_played"
    },
    {
      "id": "6709a521c85f062399d3e0ed",
      "name": "learner2.games_won"
    },
    {
      "id": "6709a521c85f062399d3e0ef",
      "name": "learner2.games_lost"
    },
    {
      "id": "6709a521c85f062399d3e0f1",
      "name": "learner2.games_tie"
    },
    {
      "id": "6709a522c85f062399d3e0f3",
      "name": "learner2.rating"
    },
    {
      "id": "6709a522c85f062399d3e0f5",
      "name": "learner1.train_correct"
    },
    {
      "id": "6709a522c85f062399d3e0f7",
      "name": "learner1.train_observed"
    },
    {
      "id": "6709a522c85f062399d3e0f9",
      "name": "learner1.games_played"
    },
    {
      "id": "6709a522c85f062399d3e0fb",
      "name": "learner1.games_won"
    },
    {
      "id": "6709a522c85f062399d3e0fd",
      "name": "learner1.games_lost"
    },
    {
      "id": "6709a522c85f062399d3e0ff",
      "name": "learner1.games_tie"
    },
    {
      "id": "6709a522c85f062399d3e101",
      "name": "learner1.rating"
    },
    {
      "id": "6709a522c85f062399d3e103",
      "name": "learner0.train_correct"
    },
    {
      "id": "6709a522c85f062399d3e105",
      "name": "learner0.train_observed"
    },
    {
      "id": "6709a522c85f062399d3e107",
      "name": "learner0.games_played"
    },
    {
      "id": "6709a522c85f062399d3e109",
      "name": "learner0.games_won"
    },
    {
      "id": "6709a522c85f062399d3e10b",
      "name": "learner0.games_lost"
    },
    {
      "id": "6709a522c85f062399d3e10d",
      "name": "learner0.games_tie"
    },
    {
      "id": "6709a522c85f062399d3e10f",
      "name": "learner0.rating"
    },
    {
      "id": "6709a522c85f062399d3e111",
      "name": "learner0.test_accuracy"
    },
    {
      "id": "6709a522c85f062399d3e113",
      "name": "learner0.relative_rating"
    },
    {
      "id": "6709a522c85f062399d3e115",
      "name": "learner1.test_accuracy"
    },
    {
      "id": "6709a522c85f062399d3e117",
      "name": "learner1.relative_rating"
    },
    {
      "id": "6709a522c85f062399d3e119",
      "name": "learner2.test_accuracy"
    },
    {
      "id": "6709a522c85f062399d3e11b",
      "name": "learner2.relative_rating"
    },
    {
      "id": "6709a522c85f062399d3e11d",
      "name": "learner3.test_accuracy"
    },
    {
      "id": "6709a522c85f062399d3e11f",
      "name": "learner3.relative_rating"
    },
    {
      "id": "6709a522c85f062399d3e121",
      "name": "learner4.test_accuracy"
    },
    {
      "id": "6709a522c85f062399d3e123",
      "name": "learner4.relative_rating"
    },
    {
      "id": "6709a522c85f062399d3e125",
      "name": "learner5.test_accuracy"
    },
    {
      "id": "6709a522c85f062399d3e127",
      "name": "learner5.relative_rating"
    },
    {
      "id": "6709a522c85f062399d3e129",
      "name": "ensemble.best_rated_accuracy"
    },
    {
      "id": "6709a522c85f062399d3e12b",
      "name": "ensemble.majority_accuracy"
    }
  ]
}