{
  "test_accuracy": {
    "steps": [
      20,
      40,
      60,
      80,
      100,
      120,
      140,
      160,
      180,
      200,
      220,
      240,
      260,
      280,
      300,
      320,
      340,
      360,
      380,
      400,
      420,
      440,
      460,
      480,
      500
    ],
    "timestamps": [
      "2024-10-04T22:01:44.704532",
      "2024-10-04T22:01:44.705110",
      "2024-10-04T22:01:44.705631",
      "2024-10-04T22:01:44.706152",
      "2024-10-04T22:01:44.706671",
      "2024-10-04T22:01:44.707209",
      "2024-10-04T22:01:44.707766",
      "2024-10-04T22:01:44.708304",
      "2024-10-04T22:01:44.708830",
      "2024-10-04T22:01:44.709303",
      "2024-10-04T22:01:44.709841",
      "2024-10-04T22:01:44.710333",
      "2024-10-04T22:01:44.710783",
      "2024-10-04T22:01:44.711334",
      "2024-10-04T22:01:44.711821",
      "2024-10-04T22:01:44.712463",
      "2024-10-04T22:01:44.712961",
      "2024-10-04T22:01:44.713503",
      "2024-10-04T22:01:44.714018",
      "2024-10-04T22:01:44.714576",
      "2024-10-04T22:01:44.715066",
      "2024-10-04T22:01:44.715622",
      "2024-10-04T22:01:44.716137",
      "2024-10-04T22:01:44.716608",
      "2024-10-04T22:01:44.717109"
    ],
    "values": [
      0.96,
      0.98,
      0.98,
      0.98,
      0.98,
      0.98,
      0.98,
      0.98,
      0.98,
      0.98,
      0.98,
      0.98,
      0.98,
      0.98,
      0.98,
      0.92,
      0.92,
      0.96,
      0.9,
      0.9,
      0.9,
      0.9,
      0.9,
      0.9,
      0.9
    ]
  },
  "train_correct": {
    "steps": [
      1,
      2,
      3,
      4,
      5,
      6,
      7,
      8,
      9,
      10,
      11,
      12,
      13,
      14,
      15,
      16,
      17,
      18,
      19,
      20,
      21,
      22,
      23,
      24,
      25,
      26,
      27,
      28,
      29,
      30,
      31,
      32,
      33,
      34,
      35,
      36,
      37,
      38,
      39,
      40,
      41,
      42,
      43,
      44,
      45,
      46,
      47,
      48,
      49,
      50,
      51,
      52,
      53,
      54,
      55,
      56,
      57,
      58,
      59,
      60,
      61,
      62,
      63,
      64,
      65,
      66,
      67,
      68,
      69,
      70,
      71,
      72,
      73,
      74,
      75,
      76,
      77,
      78,
      79,
      80,
      81,
      82,
      83,
      84,
      85,
      86,
      87,
      88,
      89,
      90,
      91,
      92,
      93,
      94,
      95,
      96,
      97,
      98,
      99,
      100,
      101,
      102,
      103,
      104,
      105,
      106,
      107,
      108,
      109,
      110,
      111,
      112,
      113,
      114,
      115,
      116,
      117,
      118,
      119,
      120,
      121,
      122,
      123,
      124,
      125,
      126,
      127,
      128,
      129,
      130,
      131,
      132,
      133,
      134,
      135,
      136,
      137,
      138,
      139,
      140,
      141,
      142,
      143,
      144,
      145,
      146,
      147,
      148,
      149,
      150,
      151,
      152,
      153,
      154,
      155,
      156,
      157,
      158,
      159,
      160,
      161,
      162,
      163,
      164,
      165,
      166,
      167,
      168,
      169,
      170,
      171,
      172,
      173,
      174,
      175,
      176,
      177,
      178,
      179,
      180,
      181,
      182,
      183,
      184,
      185,
      186,
      187,
      188,
      189,
      190,
      191,
      192,
      193,
      194,
      195,
      196,
      197,
      198,
      199,
      200,
      201,
      202,
      203,
      204,
      205,
      206,
      207,
      208,
      209,
      210,
      211,
      212,
      213,
      214,
      215,
      216,
      217,
      218,
      219,
      220,
      221,
      222,
      223,
      224,
      225,
      226,
      227,
      228,
      229,
      230,
      231,
      232,
      233,
      234,
      235,
      236,
      237,
      238,
      239,
      240,
      241,
      242,
      243,
      244,
      245,
      246,
      247,
      248,
      249,
      250,
      251,
      252,
      253,
      254,
      255,
      256,
      257,
      258,
      259,
      260,
      261,
      262,
      263,
      264,
      265,
      266,
      267,
      268,
      269,
      270,
      271,
      272,
      273,
      274,
      275,
      276,
      277,
      278,
      279,
      280,
      281,
      282,
      283,
      284,
      285,
      286,
      287,
      288,
      289,
      290,
      291,
      292,
      293,
      294,
      295,
      296,
      297,
      298,
      299,
      300,
      301,
      302,
      303,
      304,
      305,
      306,
      307,
      308,
      309,
      310,
      311,
      312,
      313,
      314,
      315,
      316,
      317,
      318,
      319,
      320,
      321,
      322,
      323,
      324,
      325,
      326,
      327,
      328,
      329,
      330,
      331,
      332,
      333,
      334,
      335,
      336,
      337,
      338,
      339,
      340,
      341,
      342,
      343,
      344,
      345,
      346,
      347,
      348,
      349,
      350,
      351,
      352,
      353,
      354,
      355,
      356,
      357,
      358,
      359,
      360,
      361,
      362,
      363,
      364,
      365,
      366,
      367,
      368,
      369,
      370,
      371,
      372,
      373,
      374,
      375,
      376,
      377,
      378,
      379,
      380,
      381,
      382,
      383,
      384,
      385,
      386,
      387,
      388,
      389,
      390,
      391,
      392,
      393,
      394,
      395,
      396,
      397,
      398,
      399,
      400,
      401,
      402,
      403,
      404,
      405,
      406,
      407,
      408,
      409,
      410,
      411,
      412,
      413,
      414,
      415,
      416,
      417,
      418,
      419,
      420,
      421,
      422,
      423,
      424,
      425,
      426,
      427,
      428,
      429,
      430,
      431,
      432,
      433,
      434,
      435,
      436,
      437,
      438,
      439,
      440,
      441,
      442,
      443,
      444,
      445,
      446,
      447,
      448,
      449,
      450,
      451,
      452,
      453,
      454,
      455,
      456,
      457,
      458,
      459,
      460,
      461,
      462,
      463,
      464,
      465,
      466,
      467,
      468,
      469,
      470,
      471,
      472,
      473,
      474,
      475,
      476,
      477,
      478,
      479,
      480,
      481,
      482,
      483,
      484,
      485,
      486,
      487,
      488,
      489,
      490,
      491,
      492,
      493,
      494,
      495,
      496,
      497,
      498,
      499,
      500
    ],
    "timestamps": [
      "2024-10-04T22:01:44.703649",
      "2024-10-04T22:01:44.703948",
      "2024-10-04T22:01:44.703992",
      "2024-10-04T22:01:44.704058",
      "2024-10-04T22:01:44.704062",
      "2024-10-04T22:01:44.704066",
      "2024-10-04T22:01:44.704069",
      "2024-10-04T22:01:44.704089",
      "2024-10-04T22:01:44.704109",
      "2024-10-04T22:01:44.704125",
      "2024-10-04T22:01:44.704144",
      "2024-10-04T22:01:44.704148",
      "2024-10-04T22:01:44.704151",
      "2024-10-04T22:01:44.704170",
      "2024-10-04T22:01:44.704189",
      "2024-10-04T22:01:44.704206",
      "2024-10-04T22:01:44.704228",
      "2024-10-04T22:01:44.704247",
      "2024-10-04T22:01:44.704265",
      "2024-10-04T22:01:44.704536",
      "2024-10-04T22:01:44.704558",
      "2024-10-04T22:01:44.704578",
      "2024-10-04T22:01:44.704596",
      "2024-10-04T22:01:44.704614",
      "2024-10-04T22:01:44.704617",
      "2024-10-04T22:01:44.704635",
      "2024-10-04T22:01:44.704653",
      "2024-10-04T22:01:44.704671",
      "2024-10-04T22:01:44.704675",
      "2024-10-04T22:01:44.704693",
      "2024-10-04T22:01:44.704711",
      "2024-10-04T22:01:44.704729",
      "2024-10-04T22:01:44.704747",
      "2024-10-04T22:01:44.704751",
      "2024-10-04T22:01:44.704769",
      "2024-10-04T22:01:44.704787",
      "2024-10-04T22:01:44.704805",
      "2024-10-04T22:01:44.704823",
      "2024-10-04T22:01:44.704841",
      "2024-10-04T22:01:44.705113",
      "2024-10-04T22:01:44.705131",
      "2024-10-04T22:01:44.705149",
      "2024-10-04T22:01:44.705167",
      "2024-10-04T22:01:44.705184",
      "2024-10-04T22:01:44.705202",
      "2024-10-04T22:01:44.705219",
      "2024-10-04T22:01:44.705223",
      "2024-10-04T22:01:44.705226",
      "2024-10-04T22:01:44.705244",
      "2024-10-04T22:01:44.705261",
      "2024-10-04T22:01:44.705265",
      "2024-10-04T22:01:44.705273",
      "2024-10-04T22:01:44.705291",
      "2024-10-04T22:01:44.705309",
      "2024-10-04T22:01:44.705312",
      "2024-10-04T22:01:44.705330",
      "2024-10-04T22:01:44.705347",
      "2024-10-04T22:01:44.705364",
      "2024-10-04T22:01:44.705368",
      "2024-10-04T22:01:44.705643",
      "2024-10-04T22:01:44.705660",
      "2024-10-04T22:01:44.705664",
      "2024-10-04T22:01:44.705681",
      "2024-10-04T22:01:44.705699",
      "2024-10-04T22:01:44.705716",
      "2024-10-04T22:01:44.705719",
      "2024-10-04T22:01:44.705748",
      "2024-10-04T22:01:44.705766",
      "2024-10-04T22:01:44.705769",
      "2024-10-04T22:01:44.705772",
      "2024-10-04T22:01:44.705791",
      "2024-10-04T22:01:44.705808",
      "2024-10-04T22:01:44.705826",
      "2024-10-04T22:01:44.705829",
      "2024-10-04T22:01:44.705847",
      "2024-10-04T22:01:44.705865",
      "2024-10-04T22:01:44.705882",
      "2024-10-04T22:01:44.705885",
      "2024-10-04T22:01:44.705903",
      "2024-10-04T22:01:44.706156",
      "2024-10-04T22:01:44.706174",
      "2024-10-04T22:01:44.706191",
      "2024-10-04T22:01:44.706209",
      "2024-10-04T22:01:44.706212",
      "2024-10-04T22:01:44.706229",
      "2024-10-04T22:01:44.706233",
      "2024-10-04T22:01:44.706252",
      "2024-10-04T22:01:44.706255",
      "2024-10-04T22:01:44.706272",
      "2024-10-04T22:01:44.706276",
      "2024-10-04T22:01:44.706279",
      "2024-10-04T22:01:44.706297",
      "2024-10-04T22:01:44.706314",
      "2024-10-04T22:01:44.706317",
      "2024-10-04T22:01:44.706335",
      "2024-10-04T22:01:44.706353",
      "2024-10-04T22:01:44.706378",
      "2024-10-04T22:01:44.706396",
      "2024-10-04T22:01:44.706399",
      "2024-10-04T22:01:44.706675",
      "2024-10-04T22:01:44.706693",
      "2024-10-04T22:01:44.706710",
      "2024-10-04T22:01:44.706714",
      "2024-10-04T22:01:44.706732",
      "2024-10-04T22:01:44.706735",
      "2024-10-04T22:01:44.706753",
      "2024-10-04T22:01:44.706771",
      "2024-10-04T22:01:44.706789",
      "2024-10-04T22:01:44.706807",
      "2024-10-04T22:01:44.706825",
      "2024-10-04T22:01:44.706842",
      "2024-10-04T22:01:44.706846",
      "2024-10-04T22:01:44.706864",
      "2024-10-04T22:01:44.706868",
      "2024-10-04T22:01:44.706885",
      "2024-10-04T22:01:44.706889",
      "2024-10-04T22:01:44.706907",
      "2024-10-04T22:01:44.706925",
      "2024-10-04T22:01:44.706943",
      "2024-10-04T22:01:44.707213",
      "2024-10-04T22:01:44.707218",
      "2024-10-04T22:01:44.707244",
      "2024-10-04T22:01:44.707248",
      "2024-10-04T22:01:44.707272",
      "2024-10-04T22:01:44.707289",
      "2024-10-04T22:01:44.707307",
      "2024-10-04T22:01:44.707310",
      "2024-10-04T22:01:44.707314",
      "2024-10-04T22:01:44.707332",
      "2024-10-04T22:01:44.707349",
      "2024-10-04T22:01:44.707375",
      "2024-10-04T22:01:44.707393",
      "2024-10-04T22:01:44.707396",
      "2024-10-04T22:01:44.707413",
      "2024-10-04T22:01:44.707417",
      "2024-10-04T22:01:44.707434",
      "2024-10-04T22:01:44.707438",
      "2024-10-04T22:01:44.707456",
      "2024-10-04T22:01:44.707473",
      "2024-10-04T22:01:44.707770",
      "2024-10-04T22:01:44.707774",
      "2024-10-04T22:01:44.707794",
      "2024-10-04T22:01:44.707813",
      "2024-10-04T22:01:44.707832",
      "2024-10-04T22:01:44.707850",
      "2024-10-04T22:01:44.707869",
      "2024-10-04T22:01:44.707888",
      "2024-10-04T22:01:44.707907",
      "2024-10-04T22:01:44.707910",
      "2024-10-04T22:01:44.707929",
      "2024-10-04T22:01:44.707947",
      "2024-10-04T22:01:44.707951",
      "2024-10-04T22:01:44.707955",
      "2024-10-04T22:01:44.707960",
      "2024-10-04T22:01:44.707979",
      "2024-10-04T22:01:44.707997",
      "2024-10-04T22:01:44.708016",
      "2024-10-04T22:01:44.708020",
      "2024-10-04T22:01:44.708038",
      "2024-10-04T22:01:44.708308",
      "2024-10-04T22:01:44.708327",
      "2024-10-04T22:01:44.708346",
      "2024-10-04T22:01:44.708364",
      "2024-10-04T22:01:44.708383",
      "2024-10-04T22:01:44.708401",
      "2024-10-04T22:01:44.708405",
      "2024-10-04T22:01:44.708408",
      "2024-10-04T22:01:44.708412",
      "2024-10-04T22:01:44.708431",
      "2024-10-04T22:01:44.708434",
      "2024-10-04T22:01:44.708453",
      "2024-10-04T22:01:44.708457",
      "2024-10-04T22:01:44.708460",
      "2024-10-04T22:01:44.708479",
      "2024-10-04T22:01:44.708487",
      "2024-10-04T22:01:44.708508",
      "2024-10-04T22:01:44.708527",
      "2024-10-04T22:01:44.708545",
      "2024-10-04T22:01:44.708549",
      "2024-10-04T22:01:44.708833",
      "2024-10-04T22:01:44.708852",
      "2024-10-04T22:01:44.708871",
      "2024-10-04T22:01:44.708874",
      "2024-10-04T22:01:44.708878",
      "2024-10-04T22:01:44.708897",
      "2024-10-04T22:01:44.708900",
      "2024-10-04T22:01:44.708919",
      "2024-10-04T22:01:44.708923",
      "2024-10-04T22:01:44.708926",
      "2024-10-04T22:01:44.708945",
      "2024-10-04T22:01:44.708963",
      "2024-10-04T22:01:44.708967",
      "2024-10-04T22:01:44.708971",
      "2024-10-04T22:01:44.708974",
      "2024-10-04T22:01:44.708993",
      "2024-10-04T22:01:44.709011",
      "2024-10-04T22:01:44.709030",
      "2024-10-04T22:01:44.709034",
      "2024-10-04T22:01:44.709037",
      "2024-10-04T22:01:44.709307",
      "2024-10-04T22:01:44.709324",
      "2024-10-04T22:01:44.709341",
      "2024-10-04T22:01:44.709358",
      "2024-10-04T22:01:44.709375",
      "2024-10-04T22:01:44.709378",
      "2024-10-04T22:01:44.709382",
      "2024-10-04T22:01:44.709399",
      "2024-10-04T22:01:44.709402",
      "2024-10-04T22:01:44.709406",
      "2024-10-04T22:01:44.709423",
      "2024-10-04T22:01:44.709439",
      "2024-10-04T22:01:44.709456",
      "2024-10-04T22:01:44.709473",
      "2024-10-04T22:01:44.709477",
      "2024-10-04T22:01:44.709493",
      "2024-10-04T22:01:44.709514",
      "2024-10-04T22:01:44.709534",
      "2024-10-04T22:01:44.709552",
      "2024-10-04T22:01:44.709570",
      "2024-10-04T22:01:44.709845",
      "2024-10-04T22:01:44.709863",
      "2024-10-04T22:01:44.709881",
      "2024-10-04T22:01:44.709884",
      "2024-10-04T22:01:44.709888",
      "2024-10-04T22:01:44.709906",
      "2024-10-04T22:01:44.709923",
      "2024-10-04T22:01:44.709940",
      "2024-10-04T22:01:44.709944",
      "2024-10-04T22:01:44.709960",
      "2024-10-04T22:01:44.709977",
      "2024-10-04T22:01:44.709981",
      "2024-10-04T22:01:44.709998",
      "2024-10-04T22:01:44.710001",
      "2024-10-04T22:01:44.710018",
      "2024-10-04T22:01:44.710035",
      "2024-10-04T22:01:44.710052",
      "2024-10-04T22:01:44.710069",
      "2024-10-04T22:01:44.710086",
      "2024-10-04T22:01:44.710090",
      "2024-10-04T22:01:44.710336",
      "2024-10-04T22:01:44.710339",
      "2024-10-04T22:01:44.710356",
      "2024-10-04T22:01:44.710360",
      "2024-10-04T22:01:44.710377",
      "2024-10-04T22:01:44.710393",
      "2024-10-04T22:01:44.710397",
      "2024-10-04T22:01:44.710400",
      "2024-10-04T22:01:44.710403",
      "2024-10-04T22:01:44.710420",
      "2024-10-04T22:01:44.710437",
      "2024-10-04T22:01:44.710440",
      "2024-10-04T22:01:44.710444",
      "2024-10-04T22:01:44.710461",
      "2024-10-04T22:01:44.710464",
      "2024-10-04T22:01:44.710481",
      "2024-10-04T22:01:44.710486",
      "2024-10-04T22:01:44.710504",
      "2024-10-04T22:01:44.710522",
      "2024-10-04T22:01:44.710539",
      "2024-10-04T22:01:44.710787",
      "2024-10-04T22:01:44.710804",
      "2024-10-04T22:01:44.710821",
      "2024-10-04T22:01:44.710838",
      "2024-10-04T22:01:44.710855",
      "2024-10-04T22:01:44.710872",
      "2024-10-04T22:01:44.710923",
      "2024-10-04T22:01:44.710941",
      "2024-10-04T22:01:44.710944",
      "2024-10-04T22:01:44.710961",
      "2024-10-04T22:01:44.710965",
      "2024-10-04T22:01:44.710982",
      "2024-10-04T22:01:44.710999",
      "2024-10-04T22:01:44.711002",
      "2024-10-04T22:01:44.711019",
      "2024-10-04T22:01:44.711036",
      "2024-10-04T22:01:44.711040",
      "2024-10-04T22:01:44.711056",
      "2024-10-04T22:01:44.711060",
      "2024-10-04T22:01:44.711077",
      "2024-10-04T22:01:44.711337",
      "2024-10-04T22:01:44.711341",
      "2024-10-04T22:01:44.711358",
      "2024-10-04T22:01:44.711375",
      "2024-10-04T22:01:44.711379",
      "2024-10-04T22:01:44.711396",
      "2024-10-04T22:01:44.711413",
      "2024-10-04T22:01:44.711430",
      "2024-10-04T22:01:44.711447",
      "2024-10-04T22:01:44.711464",
      "2024-10-04T22:01:44.711481",
      "2024-10-04T22:01:44.711484",
      "2024-10-04T22:01:44.711487",
      "2024-10-04T22:01:44.711491",
      "2024-10-04T22:01:44.711508",
      "2024-10-04T22:01:44.711511",
      "2024-10-04T22:01:44.711528",
      "2024-10-04T22:01:44.711531",
      "2024-10-04T22:01:44.711548",
      "2024-10-04T22:01:44.711565",
      "2024-10-04T22:01:44.711824",
      "2024-10-04T22:01:44.712005",
      "2024-10-04T22:01:44.712027",
      "2024-10-04T22:01:44.712044",
      "2024-10-04T22:01:44.712048",
      "2024-10-04T22:01:44.712051",
      "2024-10-04T22:01:44.712054",
      "2024-10-04T22:01:44.712058",
      "2024-10-04T22:01:44.712075",
      "2024-10-04T22:01:44.712092",
      "2024-10-04T22:01:44.712096",
      "2024-10-04T22:01:44.712099",
      "2024-10-04T22:01:44.712116",
      "2024-10-04T22:01:44.712133",
      "2024-10-04T22:01:44.712150",
      "2024-10-04T22:01:44.712167",
      "2024-10-04T22:01:44.712170",
      "2024-10-04T22:01:44.712173",
      "2024-10-04T22:01:44.712190",
      "2024-10-04T22:01:44.712208",
      "2024-10-04T22:01:44.712467",
      "2024-10-04T22:01:44.712484",
      "2024-10-04T22:01:44.712501",
      "2024-10-04T22:01:44.712518",
      "2024-10-04T22:01:44.712535",
      "2024-10-04T22:01:44.712538",
      "2024-10-04T22:01:44.712555",
      "2024-10-04T22:01:44.712572",
      "2024-10-04T22:01:44.712588",
      "2024-10-04T22:01:44.712592",
      "2024-10-04T22:01:44.712608",
      "2024-10-04T22:01:44.712625",
      "2024-10-04T22:01:44.712642",
      "2024-10-04T22:01:44.712659",
      "2024-10-04T22:01:44.712676",
      "2024-10-04T22:01:44.712679",
      "2024-10-04T22:01:44.712696",
      "2024-10-04T22:01:44.712699",
      "2024-10-04T22:01:44.712703",
      "2024-10-04T22:01:44.712706",
      "2024-10-04T22:01:44.712964",
      "2024-10-04T22:01:44.712982",
      "2024-10-04T22:01:44.712999",
      "2024-10-04T22:01:44.713016",
      "2024-10-04T22:01:44.713032",
      "2024-10-04T22:01:44.713049",
      "2024-10-04T22:01:44.713066",
      "2024-10-04T22:01:44.713083",
      "2024-10-04T22:01:44.713100",
      "2024-10-04T22:01:44.713117",
      "2024-10-04T22:01:44.713133",
      "2024-10-04T22:01:44.713150",
      "2024-10-04T22:01:44.713167",
      "2024-10-04T22:01:44.713170",
      "2024-10-04T22:01:44.713174",
      "2024-10-04T22:01:44.713191",
      "2024-10-04T22:01:44.713194",
      "2024-10-04T22:01:44.713211",
      "2024-10-04T22:01:44.713228",
      "2024-10-04T22:01:44.713245",
      "2024-10-04T22:01:44.713507",
      "2024-10-04T22:01:44.713510",
      "2024-10-04T22:01:44.713527",
      "2024-10-04T22:01:44.713544",
      "2024-10-04T22:01:44.713561",
      "2024-10-04T22:01:44.713578",
      "2024-10-04T22:01:44.713595",
      "2024-10-04T22:01:44.713613",
      "2024-10-04T22:01:44.713616",
      "2024-10-04T22:01:44.713633",
      "2024-10-04T22:01:44.713650",
      "2024-10-04T22:01:44.713667",
      "2024-10-04T22:01:44.713670",
      "2024-10-04T22:01:44.713687",
      "2024-10-04T22:01:44.713704",
      "2024-10-04T22:01:44.713708",
      "2024-10-04T22:01:44.713724",
      "2024-10-04T22:01:44.713741",
      "2024-10-04T22:01:44.713758",
      "2024-10-04T22:01:44.713775",
      "2024-10-04T22:01:44.714021",
      "2024-10-04T22:01:44.714039",
      "2024-10-04T22:01:44.714055",
      "2024-10-04T22:01:44.714073",
      "2024-10-04T22:01:44.714090",
      "2024-10-04T22:01:44.714107",
      "2024-10-04T22:01:44.714124",
      "2024-10-04T22:01:44.714141",
      "2024-10-04T22:01:44.714158",
      "2024-10-04T22:01:44.714175",
      "2024-10-04T22:01:44.714179",
      "2024-10-04T22:01:44.714182",
      "2024-10-04T22:01:44.714199",
      "2024-10-04T22:01:44.714216",
      "2024-10-04T22:01:44.714233",
      "2024-10-04T22:01:44.714250",
      "2024-10-04T22:01:44.714267",
      "2024-10-04T22:01:44.714284",
      "2024-10-04T22:01:44.714301",
      "2024-10-04T22:01:44.714317",
      "2024-10-04T22:01:44.714579",
      "2024-10-04T22:01:44.714610",
      "2024-10-04T22:01:44.714627",
      "2024-10-04T22:01:44.714644",
      "2024-10-04T22:01:44.714661",
      "2024-10-04T22:01:44.714664",
      "2024-10-04T22:01:44.714681",
      "2024-10-04T22:01:44.714684",
      "2024-10-04T22:01:44.714701",
      "2024-10-04T22:01:44.714718",
      "2024-10-04T22:01:44.714735",
      "2024-10-04T22:01:44.714738",
      "2024-10-04T22:01:44.714755",
      "2024-10-04T22:01:44.714758",
      "2024-10-04T22:01:44.714762",
      "2024-10-04T22:01:44.714765",
      "2024-10-04T22:01:44.714782",
      "2024-10-04T22:01:44.714786",
      "2024-10-04T22:01:44.714789",
      "2024-10-04T22:01:44.714806",
      "2024-10-04T22:01:44.715070",
      "2024-10-04T22:01:44.715073",
      "2024-10-04T22:01:44.715090",
      "2024-10-04T22:01:44.715093",
      "2024-10-04T22:01:44.715110",
      "2024-10-04T22:01:44.715127",
      "2024-10-04T22:01:44.715144",
      "2024-10-04T22:01:44.715161",
      "2024-10-04T22:01:44.715178",
      "2024-10-04T22:01:44.715195",
      "2024-10-04T22:01:44.715212",
      "2024-10-04T22:01:44.715215",
      "2024-10-04T22:01:44.715232",
      "2024-10-04T22:01:44.715249",
      "2024-10-04T22:01:44.715266",
      "2024-10-04T22:01:44.715283",
      "2024-10-04T22:01:44.715300",
      "2024-10-04T22:01:44.715326",
      "2024-10-04T22:01:44.715329",
      "2024-10-04T22:01:44.715346",
      "2024-10-04T22:01:44.715625",
      "2024-10-04T22:01:44.715643",
      "2024-10-04T22:01:44.715646",
      "2024-10-04T22:01:44.715663",
      "2024-10-04T22:01:44.715666",
      "2024-10-04T22:01:44.715683",
      "2024-10-04T22:01:44.715687",
      "2024-10-04T22:01:44.715704",
      "2024-10-04T22:01:44.715707",
      "2024-10-04T22:01:44.715724",
      "2024-10-04T22:01:44.715727",
      "2024-10-04T22:01:44.715745",
      "2024-10-04T22:01:44.715762",
      "2024-10-04T22:01:44.715779",
      "2024-10-04T22:01:44.715796",
      "2024-10-04T22:01:44.715813",
      "2024-10-04T22:01:44.715829",
      "2024-10-04T22:01:44.715846",
      "2024-10-04T22:01:44.715863",
      "2024-10-04T22:01:44.715880",
      "2024-10-04T22:01:44.716140",
      "2024-10-04T22:01:44.716157",
      "2024-10-04T22:01:44.716174",
      "2024-10-04T22:01:44.716177",
      "2024-10-04T22:01:44.716181",
      "2024-10-04T22:01:44.716198",
      "2024-10-04T22:01:44.716214",
      "2024-10-04T22:01:44.716218",
      "2024-10-04T22:01:44.716234",
      "2024-10-04T22:01:44.716251",
      "2024-10-04T22:01:44.716268",
      "2024-10-04T22:01:44.716272",
      "2024-10-04T22:01:44.716275",
      "2024-10-04T22:01:44.716292",
      "2024-10-04T22:01:44.716295",
      "2024-10-04T22:01:44.716298",
      "2024-10-04T22:01:44.716315",
      "2024-10-04T22:01:44.716319",
      "2024-10-04T22:01:44.716335",
      "2024-10-04T22:01:44.716352",
      "2024-10-04T22:01:44.716612",
      "2024-10-04T22:01:44.716615",
      "2024-10-04T22:01:44.716619",
      "2024-10-04T22:01:44.716636",
      "2024-10-04T22:01:44.716653",
      "2024-10-04T22:01:44.716670",
      "2024-10-04T22:01:44.716673",
      "2024-10-04T22:01:44.716691",
      "2024-10-04T22:01:44.716707",
      "2024-10-04T22:01:44.716724",
      "2024-10-04T22:01:44.716741",
      "2024-10-04T22:01:44.716758",
      "2024-10-04T22:01:44.716775",
      "2024-10-04T22:01:44.716792",
      "2024-10-04T22:01:44.716795",
      "2024-10-04T22:01:44.716799",
      "2024-10-04T22:01:44.716816",
      "2024-10-04T22:01:44.716819",
      "2024-10-04T22:01:44.716836",
      "2024-10-04T22:01:44.716853",
      "2024-10-04T22:01:44.717112"
    ],
    "values": [
      0,
      0,
      1,
      1,
      1,
      1,
      1,
      1,
      1,
      1,
      2,
      2,
      2,
      3,
      4,
      4,
      5,
      6,
      6,
      6,
      7,
      8,
      9,
      10,
      10,
      11,
      12,
      13,
      13,
      14,
      15,
      15,
      16,
      16,
      16,
      17,
      18,
      18,
      19,
      20,
      21,
      22,
      23,
      24,
      25,
      26,
      26,
      26,
      27,
      28,
      28,
      28,
      29,
      30,
      30,
      31,
      32,
      33,
      33,
      34,
      35,
      35,
      36,
      37,
      38,
      38,
      39,
      40,
      40,
      40,
      41,
      42,
      43,
      43,
      44,
      45,
      46,
      46,
      47,
      47,
      48,
      49,
      50,
      50,
      51,
      51,
      52,
      52,
      53,
      53,
      53,
      54,
      55,
      55,
      56,
      57,
      58,
      59,
      59,
      60,
      60,
      61,
      61,
      62,
      62,
      63,
      64,
      65,
      66,
      66,
      67,
      67,
      68,
      68,
      69,
      69,
      70,
      71,
      72,
      73,
      73,
      74,
      74,
      75,
      76,
      77,
      77,
      77,
      78,
      79,
      80,
      81,
      81,
      82,
      82,
      83,
      83,
      84,
      85,
      86,
      86,
      87,
      88,
      89,
      90,
      91,
      92,
      93,
      93,
      94,
      95,
      95,
      95,
      95,
      96,
      97,
      98,
      98,
      99,
      99,
      100,
      101,
      102,
      103,
      103,
      103,
      103,
      103,
      104,
      104,
      105,
      105,
      105,
      106,
      106,
      107,
      108,
      109,
      109,
      110,
      111,
      111,
      111,
      111,
      112,
      112,
      113,
      113,
      113,
      114,
      115,
      115,
      115,
      115,
      116,
      117,
      118,
      118,
      118,
      118,
      119,
      120,
      120,
      121,
      121,
      121,
      121,
      121,
      121,
      122,
      123,
      124,
      125,
      125,
      126,
      127,
      128,
      128,
      129,
      130,
      131,
      131,
      131,
      131,
      132,
      133,
      134,
      134,
      135,
      135,
      135,
      136,
      136,
      137,
      138,
      139,
      140,
      141,
      141,
      141,
      141,
      142,
      142,
      143,
      144,
      144,
      144,
      144,
      145,
      146,
      146,
      146,
      147,
      147,
      148,
      148,
      149,
      150,
      151,
      151,
      152,
      153,
      154,
      155,
      156,
      157,
      158,
      158,
      159,
      159,
      160,
      161,
      161,
      161,
      162,
      162,
      163,
      163,
      164,
      165,
      165,
      166,
      167,
      167,
      168,
      169,
      170,
      171,
      172,
      173,
      173,
      173,
      173,
      174,
      174,
      175,
      175,
      176,
      177,
      178,
      179,
      180,
      181,
      181,
      181,
      181,
      181,
      182,
      183,
      183,
      183,
      184,
      185,
      186,
      187,
      187,
      187,
      188,
      189,
      190,
      191,
      192,
      193,
      194,
      194,
      195,
      196,
      197,
      197,
      198,
      199,
      200,
      201,
      202,
      202,
      203,
      203,
      203,
      203,
      204,
      205,
      206,
      206,
      207,
      208,
      209,
      209,
      210,
      211,
      212,
      213,
      214,
      214,
      214,
      215,
      215,
      216,
      217,
      218,
      219,
      219,
      220,
      221,
      221,
      222,
      223,
      224,
      224,
      224,
      225,
      226,
      226,
      227,
      228,
      228,
      229,
      230,
      231,
      232,
      232,
      233,
      234,
      235,
      236,
      237,
      238,
      239,
      240,
      241,
      241,
      241,
      242,
      243,
      244,
      245,
      246,
      247,
      248,
      249,
      250,
      251,
      252,
      253,
      254,
      254,
      255,
      255,
      255,
      256,
      257,
      257,
      258,
      258,
      258,
      258,
      259,
      259,
      259,
      260,
      260,
      260,
      260,
      260,
      261,
      262,
      263,
      264,
      265,
      266,
      267,
      267,
      268,
      269,
      270,
      271,
      272,
      273,
      273,
      274,
      275,
      276,
      276,
      276,
      276,
      277,
      277,
      278,
      278,
      279,
      279,
      280,
      281,
      282,
      283,
      284,
      285,
      286,
      287,
      288,
      289,
      290,
      291,
      291,
      291,
      292,
      293,
      293,
      294,
      295,
      296,
      296,
      296,
      297,
      297,
      297,
      297,
      297,
      298,
      299,
      300,
      300,
      300,
      301,
      302,
      303,
      303,
      304,
      305,
      306,
      307,
      308,
      308,
      309,
      309,
      309,
      310,
      310,
      311,
      312,
      313
    ]
  },
  "train_observed": {
    "steps": [
      1,
      2,
      3,
      4,
      5,
      6,
      7,
      8,
      9,
      10,
      11,
      12,
      13,
      14,
      15,
      16,
      17,
      18,
      19,
      20,
      21,
      22,
      23,
      24,
      25,
      26,
      27,
      28,
      29,
      30,
      31,
      32,
      33,
      34,
      35,
      36,
      37,
      38,
      39,
      40,
      41,
      42,
      43,
      44,
      45,
      46,
      47,
      48,
      49,
      50,
      51,
      52,
      53,
      54,
      55,
      56,
      57,
      58,
      59,
      60,
      61,
      62,
      63,
      64,
      65,
      66,
      67,
      68,
      69,
      70,
      71,
      72,
      73,
      74,
      75,
      76,
      77,
      78,
      79,
      80,
      81,
      82,
      83,
      84,
      85,
      86,
      87,
      88,
      89,
      90,
      91,
      92,
      93,
      94,
      95,
      96,
      97,
      98,
      99,
      100,
      101,
      102,
      103,
      104,
      105,
      106,
      107,
      108,
      109,
      110,
      111,
      112,
      113,
      114,
      115,
      116,
      117,
      118,
      119,
      120,
      121,
      122,
      123,
      124,
      125,
      126,
      127,
      128,
      129,
      130,
      131,
      132,
      133,
      134,
      135,
      136,
      137,
      138,
      139,
      140,
      141,
      142,
      143,
      144,
      145,
      146,
      147,
      148,
      149,
      150,
      151,
      152,
      153,
      154,
      155,
      156,
      157,
      158,
      159,
      160,
      161,
      162,
      163,
      164,
      165,
      166,
      167,
      168,
      169,
      170,
      171,
      172,
      173,
      174,
      175,
      176,
      177,
      178,
      179,
      180,
      181,
      182,
      183,
      184,
      185,
      186,
      187,
      188,
      189,
      190,
      191,
      192,
      193,
      194,
      195,
      196,
      197,
      198,
      199,
      200,
      201,
      202,
      203,
      204,
      205,
      206,
      207,
      208,
      209,
      210,
      211,
      212,
      213,
      214,
      215,
      216,
      217,
      218,
      219,
      220,
      221,
      222,
      223,
      224,
      225,
      226,
      227,
      228,
      229,
      230,
      231,
      232,
      233,
      234,
      235,
      236,
      237,
      238,
      239,
      240,
      241,
      242,
      243,
      244,
      245,
      246,
      247,
      248,
      249,
      250,
      251,
      252,
      253,
      254,
      255,
      256,
      257,
      258,
      259,
      260,
      261,
      262,
      263,
      264,
      265,
      266,
      267,
      268,
      269,
      270,
      271,
      272,
      273,
      274,
      275,
      276,
      277,
      278,
      279,
      280,
      281,
      282,
      283,
      284,
      285,
      286,
      287,
      288,
      289,
      290,
      291,
      292,
      293,
      294,
      295,
      296,
      297,
      298,
      299,
      300,
      301,
      302,
      303,
      304,
      305,
      306,
      307,
      308,
      309,
      310,
      311,
      312,
      313,
      314,
      315,
      316,
      317,
      318,
      319,
      320,
      321,
      322,
      323,
      324,
      325,
      326,
      327,
      328,
      329,
      330,
      331,
      332,
      333,
      334,
      335,
      336,
      337,
      338,
      339,
      340,
      341,
      342,
      343,
      344,
      345,
      346,
      347,
      348,
      349,
      350,
      351,
      352,
      353,
      354,
      355,
      356,
      357,
      358,
      359,
      360,
      361,
      362,
      363,
      364,
      365,
      366,
      367,
      368,
      369,
      370,
      371,
      372,
      373,
      374,
      375,
      376,
      377,
      378,
      379,
      380,
      381,
      382,
      383,
      384,
      385,
      386,
      387,
      388,
      389,
      390,
      391,
      392,
      393,
      394,
      395,
      396,
      397,
      398,
      399,
      400,
      401,
      402,
      403,
      404,
      405,
      406,
      407,
      408,
      409,
      410,
      411,
      412,
      413,
      414,
      415,
      416,
      417,
      418,
      419,
      420,
      421,
      422,
      423,
      424,
      425,
      426,
      427,
      428,
      429,
      430,
      431,
      432,
      433,
      434,
      435,
      436,
      437,
      438,
      439,
      440,
      441,
      442,
      443,
      444,
      445,
      446,
      447,
      448,
      449,
      450,
      451,
      452,
      453,
      454,
      455,
      456,
      457,
      458,
      459,
      460,
      461,
      462,
      463,
      464,
      465,
      466,
      467,
      468,
      469,
      470,
      471,
      472,
      473,
      474,
      475,
      476,
      477,
      478,
      479,
      480,
      481,
      482,
      483,
      484,
      485,
      486,
      487,
      488,
      489,
      490,
      491,
      492,
      493,
      494,
      495,
      496,
      497,
      498,
      499,
      500
    ],
    "timestamps": [
      "2024-10-04T22:01:44.703633",
      "2024-10-04T22:01:44.703944",
      "2024-10-04T22:01:44.703989",
      "2024-10-04T22:01:44.704056",
      "2024-10-04T22:01:44.704060",
      "2024-10-04T22:01:44.704064",
      "2024-10-04T22:01:44.704067",
      "2024-10-04T22:01:44.704087",
      "2024-10-04T22:01:44.704107",
      "2024-10-04T22:01:44.704124",
      "2024-10-04T22:01:44.704142",
      "2024-10-04T22:01:44.704146",
      "2024-10-04T22:01:44.704149",
      "2024-10-04T22:01:44.704168",
      "2024-10-04T22:01:44.704187",
      "2024-10-04T22:01:44.704204",
      "2024-10-04T22:01:44.704222",
      "2024-10-04T22:01:44.704245",
      "2024-10-04T22:01:44.704263",
      "2024-10-04T22:01:44.704534",
      "2024-10-04T22:01:44.704556",
      "2024-10-04T22:01:44.704576",
      "2024-10-04T22:01:44.704594",
      "2024-10-04T22:01:44.704612",
      "2024-10-04T22:01:44.704616",
      "2024-10-04T22:01:44.704633",
      "2024-10-04T22:01:44.704651",
      "2024-10-04T22:01:44.704669",
      "2024-10-04T22:01:44.704673",
      "2024-10-04T22:01:44.704691",
      "2024-10-04T22:01:44.704709",
      "2024-10-04T22:01:44.704727",
      "2024-10-04T22:01:44.704745",
      "2024-10-04T22:01:44.704749",
      "2024-10-04T22:01:44.704767",
      "2024-10-04T22:01:44.704785",
      "2024-10-04T22:01:44.704803",
      "2024-10-04T22:01:44.704821",
      "2024-10-04T22:01:44.704839",
      "2024-10-04T22:01:44.705112",
      "2024-10-04T22:01:44.705129",
      "2024-10-04T22:01:44.705147",
      "2024-10-04T22:01:44.705165",
      "2024-10-04T22:01:44.705183",
      "2024-10-04T22:01:44.705200",
      "2024-10-04T22:01:44.705218",
      "2024-10-04T22:01:44.705221",
      "2024-10-04T22:01:44.705224",
      "2024-10-04T22:01:44.705242",
      "2024-10-04T22:01:44.705259",
      "2024-10-04T22:01:44.705263",
      "2024-10-04T22:01:44.705271",
      "2024-10-04T22:01:44.705289",
      "2024-10-04T22:01:44.705307",
      "2024-10-04T22:01:44.705310",
      "2024-10-04T22:01:44.705328",
      "2024-10-04T22:01:44.705345",
      "2024-10-04T22:01:44.705363",
      "2024-10-04T22:01:44.705366",
      "2024-10-04T22:01:44.705633",
      "2024-10-04T22:01:44.705659",
      "2024-10-04T22:01:44.705662",
      "2024-10-04T22:01:44.705679",
      "2024-10-04T22:01:44.705697",
      "2024-10-04T22:01:44.705714",
      "2024-10-04T22:01:44.705718",
      "2024-10-04T22:01:44.705746",
      "2024-10-04T22:01:44.705764",
      "2024-10-04T22:01:44.705767",
      "2024-10-04T22:01:44.705771",
      "2024-10-04T22:01:44.705789",
      "2024-10-04T22:01:44.705806",
      "2024-10-04T22:01:44.705824",
      "2024-10-04T22:01:44.705827",
      "2024-10-04T22:01:44.705845",
      "2024-10-04T22:01:44.705863",
      "2024-10-04T22:01:44.705880",
      "2024-10-04T22:01:44.705884",
      "2024-10-04T22:01:44.705901",
      "2024-10-04T22:01:44.706154",
      "2024-10-04T22:01:44.706172",
      "2024-10-04T22:01:44.706189",
      "2024-10-04T22:01:44.706207",
      "2024-10-04T22:01:44.706210",
      "2024-10-04T22:01:44.706228",
      "2024-10-04T22:01:44.706231",
      "2024-10-04T22:01:44.706250",
      "2024-10-04T22:01:44.706253",
      "2024-10-04T22:01:44.706271",
      "2024-10-04T22:01:44.706274",
      "2024-10-04T22:01:44.706278",
      "2024-10-04T22:01:44.706295",
      "2024-10-04T22:01:44.706312",
      "2024-10-04T22:01:44.706316",
      "2024-10-04T22:01:44.706333",
      "2024-10-04T22:01:44.706351",
      "2024-10-04T22:01:44.706376",
      "2024-10-04T22:01:44.706394",
      "2024-10-04T22:01:44.706398",
      "2024-10-04T22:01:44.706673",
      "2024-10-04T22:01:44.706691",
      "2024-10-04T22:01:44.706709",
      "2024-10-04T22:01:44.706712",
      "2024-10-04T22:01:44.706730",
      "2024-10-04T22:01:44.706734",
      "2024-10-04T22:01:44.706751",
      "2024-10-04T22:01:44.706769",
      "2024-10-04T22:01:44.706787",
      "2024-10-04T22:01:44.706805",
      "2024-10-04T22:01:44.706823",
      "2024-10-04T22:01:44.706841",
      "2024-10-04T22:01:44.706844",
      "2024-10-04T22:01:44.706862",
      "2024-10-04T22:01:44.706866",
      "2024-10-04T22:01:44.706884",
      "2024-10-04T22:01:44.706887",
      "2024-10-04T22:01:44.706905",
      "2024-10-04T22:01:44.706923",
      "2024-10-04T22:01:44.706941",
      "2024-10-04T22:01:44.707211",
      "2024-10-04T22:01:44.707216",
      "2024-10-04T22:01:44.707242",
      "2024-10-04T22:01:44.707246",
      "2024-10-04T22:01:44.707270",
      "2024-10-04T22:01:44.707288",
      "2024-10-04T22:01:44.707305",
      "2024-10-04T22:01:44.707309",
      "2024-10-04T22:01:44.707312",
      "2024-10-04T22:01:44.707330",
      "2024-10-04T22:01:44.707348",
      "2024-10-04T22:01:44.707374",
      "2024-10-04T22:01:44.707391",
      "2024-10-04T22:01:44.707394",
      "2024-10-04T22:01:44.707412",
      "2024-10-04T22:01:44.707415",
      "2024-10-04T22:01:44.707432",
      "2024-10-04T22:01:44.707436",
      "2024-10-04T22:01:44.707454",
      "2024-10-04T22:01:44.707471",
      "2024-10-04T22:01:44.707768",
      "2024-10-04T22:01:44.707772",
      "2024-10-04T22:01:44.707792",
      "2024-10-04T22:01:44.707811",
      "2024-10-04T22:01:44.707830",
      "2024-10-04T22:01:44.707848",
      "2024-10-04T22:01:44.707867",
      "2024-10-04T22:01:44.707886",
      "2024-10-04T22:01:44.707905",
      "2024-10-04T22:01:44.707908",
      "2024-10-04T22:01:44.707927",
      "2024-10-04T22:01:44.707945",
      "2024-10-04T22:01:44.707949",
      "2024-10-04T22:01:44.707953",
      "2024-10-04T22:01:44.707958",
      "2024-10-04T22:01:44.707977",
      "2024-10-04T22:01:44.707995",
      "2024-10-04T22:01:44.708014",
      "2024-10-04T22:01:44.708018",
      "2024-10-04T22:01:44.708036",
      "2024-10-04T22:01:44.708306",
      "2024-10-04T22:01:44.708325",
      "2024-10-04T22:01:44.708344",
      "2024-10-04T22:01:44.708362",
      "2024-10-04T22:01:44.708381",
      "2024-10-04T22:01:44.708399",
      "2024-10-04T22:01:44.708403",
      "2024-10-04T22:01:44.708407",
      "2024-10-04T22:01:44.708410",
      "2024-10-04T22:01:44.708429",
      "2024-10-04T22:01:44.708433",
      "2024-10-04T22:01:44.708451",
      "2024-10-04T22:01:44.708455",
      "2024-10-04T22:01:44.708458",
      "2024-10-04T22:01:44.708477",
      "2024-10-04T22:01:44.708485",
      "2024-10-04T22:01:44.708506",
      "2024-10-04T22:01:44.708525",
      "2024-10-04T22:01:44.708544",
      "2024-10-04T22:01:44.708547",
      "2024-10-04T22:01:44.708832",
      "2024-10-04T22:01:44.708850",
      "2024-10-04T22:01:44.708869",
      "2024-10-04T22:01:44.708873",
      "2024-10-04T22:01:44.708876",
      "2024-10-04T22:01:44.708895",
      "2024-10-04T22:01:44.708899",
      "2024-10-04T22:01:44.708917",
      "2024-10-04T22:01:44.708921",
      "2024-10-04T22:01:44.708924",
      "2024-10-04T22:01:44.708943",
      "2024-10-04T22:01:44.708962",
      "2024-10-04T22:01:44.708965",
      "2024-10-04T22:01:44.708969",
      "2024-10-04T22:01:44.708972",
      "2024-10-04T22:01:44.708991",
      "2024-10-04T22:01:44.709010",
      "2024-10-04T22:01:44.709028",
      "2024-10-04T22:01:44.709032",
      "2024-10-04T22:01:44.709035",
      "2024-10-04T22:01:44.709305",
      "2024-10-04T22:01:44.709323",
      "2024-10-04T22:01:44.709340",
      "2024-10-04T22:01:44.709357",
      "2024-10-04T22:01:44.709373",
      "2024-10-04T22:01:44.709377",
      "2024-10-04T22:01:44.709380",
      "2024-10-04T22:01:44.709397",
      "2024-10-04T22:01:44.709401",
      "2024-10-04T22:01:44.709404",
      "2024-10-04T22:01:44.709421",
      "2024-10-04T22:01:44.709438",
      "2024-10-04T22:01:44.709455",
      "2024-10-04T22:01:44.709472",
      "2024-10-04T22:01:44.709475",
      "2024-10-04T22:01:44.709492",
      "2024-10-04T22:01:44.709512",
      "2024-10-04T22:01:44.709532",
      "2024-10-04T22:01:44.709550",
      "2024-10-04T22:01:44.709568",
      "2024-10-04T22:01:44.709843",
      "2024-10-04T22:01:44.709861",
      "2024-10-04T22:01:44.709879",
      "2024-10-04T22:01:44.709882",
      "2024-10-04T22:01:44.709886",
      "2024-10-04T22:01:44.709904",
      "2024-10-04T22:01:44.709922",
      "2024-10-04T22:01:44.709939",
      "2024-10-04T22:01:44.709942",
      "2024-10-04T22:01:44.709959",
      "2024-10-04T22:01:44.709976",
      "2024-10-04T22:01:44.709979",
      "2024-10-04T22:01:44.709996",
      "2024-10-04T22:01:44.710000",
      "2024-10-04T22:01:44.710017",
      "2024-10-04T22:01:44.710034",
      "2024-10-04T22:01:44.710051",
      "2024-10-04T22:01:44.710068",
      "2024-10-04T22:01:44.710085",
      "2024-10-04T22:01:44.710088",
      "2024-10-04T22:01:44.710334",
      "2024-10-04T22:01:44.710338",
      "2024-10-04T22:01:44.710355",
      "2024-10-04T22:01:44.710358",
      "2024-10-04T22:01:44.710375",
      "2024-10-04T22:01:44.710392",
      "2024-10-04T22:01:44.710395",
      "2024-10-04T22:01:44.710399",
      "2024-10-04T22:01:44.710402",
      "2024-10-04T22:01:44.710419",
      "2024-10-04T22:01:44.710435",
      "2024-10-04T22:01:44.710439",
      "2024-10-04T22:01:44.710442",
      "2024-10-04T22:01:44.710459",
      "2024-10-04T22:01:44.710463",
      "2024-10-04T22:01:44.710480",
      "2024-10-04T22:01:44.710484",
      "2024-10-04T22:01:44.710502",
      "2024-10-04T22:01:44.710520",
      "2024-10-04T22:01:44.710537",
      "2024-10-04T22:01:44.710785",
      "2024-10-04T22:01:44.710803",
      "2024-10-04T22:01:44.710819",
      "2024-10-04T22:01:44.710836",
      "2024-10-04T22:01:44.710853",
      "2024-10-04T22:01:44.710870",
      "2024-10-04T22:01:44.710921",
      "2024-10-04T22:01:44.710939",
      "2024-10-04T22:01:44.710942",
      "2024-10-04T22:01:44.710959",
      "2024-10-04T22:01:44.710963",
      "2024-10-04T22:01:44.710980",
      "2024-10-04T22:01:44.710997",
      "2024-10-04T22:01:44.711001",
      "2024-10-04T22:01:44.711018",
      "2024-10-04T22:01:44.711035",
      "2024-10-04T22:01:44.711038",
      "2024-10-04T22:01:44.711055",
      "2024-10-04T22:01:44.711058",
      "2024-10-04T22:01:44.711075",
      "2024-10-04T22:01:44.711336",
      "2024-10-04T22:01:44.711339",
      "2024-10-04T22:01:44.711357",
      "2024-10-04T22:01:44.711374",
      "2024-10-04T22:01:44.711377",
      "2024-10-04T22:01:44.711394",
      "2024-10-04T22:01:44.711411",
      "2024-10-04T22:01:44.711428",
      "2024-10-04T22:01:44.711445",
      "2024-10-04T22:01:44.711462",
      "2024-10-04T22:01:44.711479",
      "2024-10-04T22:01:44.711482",
      "2024-10-04T22:01:44.711486",
      "2024-10-04T22:01:44.711489",
      "2024-10-04T22:01:44.711506",
      "2024-10-04T22:01:44.711509",
      "2024-10-04T22:01:44.711526",
      "2024-10-04T22:01:44.711529",
      "2024-10-04T22:01:44.711546",
      "2024-10-04T22:01:44.711563",
      "2024-10-04T22:01:44.711823",
      "2024-10-04T22:01:44.712002",
      "2024-10-04T22:01:44.712025",
      "2024-10-04T22:01:44.712043",
      "2024-10-04T22:01:44.712046",
      "2024-10-04T22:01:44.712050",
      "2024-10-04T22:01:44.712053",
      "2024-10-04T22:01:44.712056",
      "2024-10-04T22:01:44.712073",
      "2024-10-04T22:01:44.712090",
      "2024-10-04T22:01:44.712094",
      "2024-10-04T22:01:44.712097",
      "2024-10-04T22:01:44.712114",
      "2024-10-04T22:01:44.712131",
      "2024-10-04T22:01:44.712148",
      "2024-10-04T22:01:44.712165",
      "2024-10-04T22:01:44.712168",
      "2024-10-04T22:01:44.712172",
      "2024-10-04T22:01:44.712189",
      "2024-10-04T22:01:44.712206",
      "2024-10-04T22:01:44.712465",
      "2024-10-04T22:01:44.712482",
      "2024-10-04T22:01:44.712499",
      "2024-10-04T22:01:44.712516",
      "2024-10-04T22:01:44.712533",
      "2024-10-04T22:01:44.712536",
      "2024-10-04T22:01:44.712553",
      "2024-10-04T22:01:44.712570",
      "2024-10-04T22:01:44.712587",
      "2024-10-04T22:01:44.712590",
      "2024-10-04T22:01:44.712607",
      "2024-10-04T22:01:44.712623",
      "2024-10-04T22:01:44.712640",
      "2024-10-04T22:01:44.712657",
      "2024-10-04T22:01:44.712674",
      "2024-10-04T22:01:44.712678",
      "2024-10-04T22:01:44.712694",
      "2024-10-04T22:01:44.712698",
      "2024-10-04T22:01:44.712701",
      "2024-10-04T22:01:44.712704",
      "2024-10-04T22:01:44.712963",
      "2024-10-04T22:01:44.712980",
      "2024-10-04T22:01:44.712997",
      "2024-10-04T22:01:44.713014",
      "2024-10-04T22:01:44.713031",
      "2024-10-04T22:01:44.713048",
      "2024-10-04T22:01:44.713065",
      "2024-10-04T22:01:44.713081",
      "2024-10-04T22:01:44.713098",
      "2024-10-04T22:01:44.713115",
      "2024-10-04T22:01:44.713132",
      "2024-10-04T22:01:44.713149",
      "2024-10-04T22:01:44.713165",
      "2024-10-04T22:01:44.713169",
      "2024-10-04T22:01:44.713172",
      "2024-10-04T22:01:44.713189",
      "2024-10-04T22:01:44.713192",
      "2024-10-04T22:01:44.713209",
      "2024-10-04T22:01:44.713226",
      "2024-10-04T22:01:44.713243",
      "2024-10-04T22:01:44.713505",
      "2024-10-04T22:01:44.713509",
      "2024-10-04T22:01:44.713526",
      "2024-10-04T22:01:44.713543",
      "2024-10-04T22:01:44.713560",
      "2024-10-04T22:01:44.713576",
      "2024-10-04T22:01:44.713593",
      "2024-10-04T22:01:44.713611",
      "2024-10-04T22:01:44.713614",
      "2024-10-04T22:01:44.713631",
      "2024-10-04T22:01:44.713648",
      "2024-10-04T22:01:44.713665",
      "2024-10-04T22:01:44.713669",
      "2024-10-04T22:01:44.713686",
      "2024-10-04T22:01:44.713703",
      "2024-10-04T22:01:44.713706",
      "2024-10-04T22:01:44.713723",
      "2024-10-04T22:01:44.713740",
      "2024-10-04T22:01:44.713757",
      "2024-10-04T22:01:44.713774",
      "2024-10-04T22:01:44.714020",
      "2024-10-04T22:01:44.714037",
      "2024-10-04T22:01:44.714054",
      "2024-10-04T22:01:44.714071",
      "2024-10-04T22:01:44.714088",
      "2024-10-04T22:01:44.714105",
      "2024-10-04T22:01:44.714122",
      "2024-10-04T22:01:44.714139",
      "2024-10-04T22:01:44.714156",
      "2024-10-04T22:01:44.714174",
      "2024-10-04T22:01:44.714177",
      "2024-10-04T22:01:44.714180",
      "2024-10-04T22:01:44.714198",
      "2024-10-04T22:01:44.714215",
      "2024-10-04T22:01:44.714231",
      "2024-10-04T22:01:44.714248",
      "2024-10-04T22:01:44.714265",
      "2024-10-04T22:01:44.714282",
      "2024-10-04T22:01:44.714299",
      "2024-10-04T22:01:44.714316",
      "2024-10-04T22:01:44.714578",
      "2024-10-04T22:01:44.714608",
      "2024-10-04T22:01:44.714625",
      "2024-10-04T22:01:44.714642",
      "2024-10-04T22:01:44.714659",
      "2024-10-04T22:01:44.714662",
      "2024-10-04T22:01:44.714679",
      "2024-10-04T22:01:44.714682",
      "2024-10-04T22:01:44.714699",
      "2024-10-04T22:01:44.714716",
      "2024-10-04T22:01:44.714733",
      "2024-10-04T22:01:44.714736",
      "2024-10-04T22:01:44.714753",
      "2024-10-04T22:01:44.714757",
      "2024-10-04T22:01:44.714760",
      "2024-10-04T22:01:44.714763",
      "2024-10-04T22:01:44.714780",
      "2024-10-04T22:01:44.714784",
      "2024-10-04T22:01:44.714787",
      "2024-10-04T22:01:44.714804",
      "2024-10-04T22:01:44.715068",
      "2024-10-04T22:01:44.715071",
      "2024-10-04T22:01:44.715088",
      "2024-10-04T22:01:44.715092",
      "2024-10-04T22:01:44.715109",
      "2024-10-04T22:01:44.715126",
      "2024-10-04T22:01:44.715143",
      "2024-10-04T22:01:44.715159",
      "2024-10-04T22:01:44.715176",
      "2024-10-04T22:01:44.715193",
      "2024-10-04T22:01:44.715210",
      "2024-10-04T22:01:44.715214",
      "2024-10-04T22:01:44.715231",
      "2024-10-04T22:01:44.715248",
      "2024-10-04T22:01:44.715265",
      "2024-10-04T22:01:44.715281",
      "2024-10-04T22:01:44.715298",
      "2024-10-04T22:01:44.715324",
      "2024-10-04T22:01:44.715327",
      "2024-10-04T22:01:44.715345",
      "2024-10-04T22:01:44.715624",
      "2024-10-04T22:01:44.715641",
      "2024-10-04T22:01:44.715644",
      "2024-10-04T22:01:44.715661",
      "2024-10-04T22:01:44.715665",
      "2024-10-04T22:01:44.715682",
      "2024-10-04T22:01:44.715685",
      "2024-10-04T22:01:44.715702",
      "2024-10-04T22:01:44.715705",
      "2024-10-04T22:01:44.715722",
      "2024-10-04T22:01:44.715726",
      "2024-10-04T22:01:44.715743",
      "2024-10-04T22:01:44.715760",
      "2024-10-04T22:01:44.715777",
      "2024-10-04T22:01:44.715794",
      "2024-10-04T22:01:44.715811",
      "2024-10-04T22:01:44.715828",
      "2024-10-04T22:01:44.715844",
      "2024-10-04T22:01:44.715861",
      "2024-10-04T22:01:44.715878",
      "2024-10-04T22:01:44.716138",
      "2024-10-04T22:01:44.716155",
      "2024-10-04T22:01:44.716172",
      "2024-10-04T22:01:44.716176",
      "2024-10-04T22:01:44.716179",
      "2024-10-04T22:01:44.716196",
      "2024-10-04T22:01:44.716213",
      "2024-10-04T22:01:44.716216",
      "2024-10-04T22:01:44.716233",
      "2024-10-04T22:01:44.716250",
      "2024-10-04T22:01:44.716267",
      "2024-10-04T22:01:44.716270",
      "2024-10-04T22:01:44.716273",
      "2024-10-04T22:01:44.716290",
      "2024-10-04T22:01:44.716294",
      "2024-10-04T22:01:44.716297",
      "2024-10-04T22:01:44.716314",
      "2024-10-04T22:01:44.716317",
      "2024-10-04T22:01:44.716334",
      "2024-10-04T22:01:44.716351",
      "2024-10-04T22:01:44.716610",
      "2024-10-04T22:01:44.716614",
      "2024-10-04T22:01:44.716617",
      "2024-10-04T22:01:44.716634",
      "2024-10-04T22:01:44.716651",
      "2024-10-04T22:01:44.716668",
      "2024-10-04T22:01:44.716672",
      "2024-10-04T22:01:44.716689",
      "2024-10-04T22:01:44.716706",
      "2024-10-04T22:01:44.716723",
      "2024-10-04T22:01:44.716740",
      "2024-10-04T22:01:44.716757",
      "2024-10-04T22:01:44.716773",
      "2024-10-04T22:01:44.716790",
      "2024-10-04T22:01:44.716794",
      "2024-10-04T22:01:44.716797",
      "2024-10-04T22:01:44.716814",
      "2024-10-04T22:01:44.716818",
      "2024-10-04T22:01:44.716834",
      "2024-10-04T22:01:44.716851",
      "2024-10-04T22:01:44.717110"
    ],
    "values": [
      0,
      1,
      2,
      3,
      3,
      3,
      3,
      4,
      5,
      6,
      7,
      7,
      7,
      8,
      9,
      10,
      11,
      12,
      13,
      14,
      15,
      16,
      17,
      18,
      18,
      19,
      20,
      21,
      21,
      22,
      23,
      24,
      25,
      25,
      26,
      27,
      28,
      29,
      30,
      31,
      32,
      33,
      34,
      35,
      36,
      37,
      37,
      37,
      38,
      39,
      39,
      39,
      40,
      41,
      41,
      42,
      43,
      44,
      44,
      45,
      46,
      46,
      47,
      48,
      49,
      49,
      50,
      51,
      51,
      51,
      52,
      53,
      54,
      54,
      55,
      56,
      57,
      57,
      58,
      58,
      59,
      60,
      61,
      61,
      62,
      62,
      63,
      63,
      64,
      64,
      64,
      65,
      66,
      66,
      67,
      68,
      69,
      70,
      70,
      71,
      72,
      73,
      73,
      74,
      74,
      75,
      76,
      77,
      78,
      79,
      80,
      80,
      81,
      81,
      82,
      82,
      83,
      84,
      85,
      86,
      86,
      87,
      87,
      88,
      89,
      90,
      90,
      90,
      91,
      92,
      93,
      94,
      94,
      95,
      95,
      96,
      96,
      97,
      98,
      99,
      99,
      100,
      101,
      102,
      103,
      104,
      105,
      106,
      106,
      107,
      108,
      108,
      108,
      108,
      109,
      110,
      111,
      111,
      112,
      112,
      113,
      114,
      115,
      116,
      117,
      117,
      117,
      117,
      118,
      118,
      119,
      119,
      119,
      120,
      120,
      121,
      122,
      123,
      123,
      124,
      125,
      126,
      126,
      126,
      127,
      127,
      128,
      128,
      128,
      129,
      130,
      130,
      130,
      130,
      131,
      132,
      133,
      133,
      133,
      133,
      134,
      135,
      136,
      137,
      137,
      137,
      138,
      138,
      138,
      139,
      140,
      141,
      142,
      142,
      143,
      144,
      145,
      146,
      147,
      148,
      149,
      150,
      150,
      150,
      151,
      152,
      153,
      153,
      154,
      155,
      155,
      156,
      156,
      157,
      158,
      159,
      160,
      161,
      161,
      161,
      161,
      162,
      162,
      163,
      164,
      164,
      164,
      164,
      165,
      166,
      166,
      166,
      167,
      167,
      168,
      168,
      169,
      170,
      171,
      171,
      172,
      173,
      174,
      175,
      176,
      177,
      178,
      178,
      179,
      179,
      180,
      181,
      181,
      182,
      183,
      183,
      184,
      184,
      185,
      186,
      186,
      187,
      188,
      188,
      189,
      190,
      191,
      192,
      193,
      194,
      194,
      194,
      194,
      195,
      195,
      196,
      196,
      197,
      198,
      199,
      200,
      201,
      202,
      202,
      202,
      202,
      202,
      203,
      204,
      204,
      204,
      205,
      206,
      207,
      208,
      208,
      208,
      209,
      210,
      211,
      212,
      213,
      214,
      215,
      215,
      216,
      217,
      218,
      218,
      219,
      220,
      221,
      222,
      223,
      223,
      224,
      224,
      224,
      224,
      225,
      226,
      227,
      228,
      229,
      230,
      231,
      232,
      233,
      234,
      235,
      236,
      237,
      237,
      237,
      238,
      238,
      239,
      240,
      241,
      242,
      242,
      243,
      244,
      245,
      246,
      247,
      248,
      248,
      249,
      250,
      251,
      251,
      252,
      253,
      253,
      254,
      255,
      256,
      257,
      257,
      258,
      259,
      260,
      261,
      262,
      263,
      264,
      265,
      266,
      266,
      266,
      267,
      268,
      269,
      270,
      271,
      272,
      273,
      274,
      275,
      276,
      277,
      278,
      279,
      279,
      280,
      280,
      281,
      282,
      283,
      283,
      284,
      284,
      284,
      284,
      285,
      285,
      285,
      286,
      286,
      286,
      287,
      287,
      288,
      289,
      290,
      291,
      292,
      293,
      294,
      294,
      295,
      296,
      297,
      298,
      299,
      300,
      300,
      301,
      302,
      303,
      303,
      304,
      304,
      305,
      305,
      306,
      306,
      307,
      307,
      308,
      309,
      310,
      311,
      312,
      313,
      314,
      315,
      316,
      317,
      318,
      319,
      319,
      319,
      320,
      321,
      321,
      322,
      323,
      324,
      324,
      324,
      325,
      325,
      325,
      326,
      326,
      327,
      328,
      329,
      329,
      329,
      330,
      331,
      332,
      332,
      333,
      334,
      335,
      336,
      337,
      338,
      339,
      339,
      339,
      340,
      340,
      341,
      342,
      343
    ]
  }
}