{
  "metrics": [
    {
      "id": "6709a16cc85f062399d3c4a5",
      "name": "learner2.train_correct"
    },
    {
      "id": "6709a16cc85f062399d3c4a7",
      "name": "learner2.train_observed"
    },
    {
      "id": "6709a16cc85f062399d3c4a9",
      "name": "learner2.games_played"
    },
    {
      "id": "6709a16cc85f062399d3c4ab",
      "name": "learner2.games_won"
    },
    {
      "id": "6709a16cc85f062399d3c4ad",
      "name": "learner2.games_lost"
    },
    {
      "id": "6709a16cc85f062399d3c4af",
      "name": "learner2.games_tie"
    },
    {
      "id": "6709a16cc85f062399d3c4b1",
      "name": "learner2.rating"
    },
    {
      "id": "6709a16cc85f062399d3c4b3",
      "name": "learner1.train_correct"
    },
    {
      "id": "6709a16cc85f062399d3c4b5",
      "name": "learner1.train_observed"
    },
    {
      "id": "6709a16cc85f062399d3c4b7",
      "name": "learner1.games_played"
    },
    {
      "id": "6709a16cc85f062399d3c4b9",
      "name": "learner1.games_won"
    },
    {
      "id": "6709a16cc85f062399d3c4bb",
      "name": "learner1.games_lost"
    },
    {
      "id": "6709a16cc85f062399d3c4bd",
      "name": "learner1.games_tie"
    },
    {
      "id": "6709a16cc85f062399d3c4bf",
      "name": "learner1.rating"
    },
    {
      "id": "6709a16cc85f062399d3c4c1",
      "name": "learner4.train_correct"
    },
    {
      "id": "6709a16cc85f062399d3c4c3",
      "name": "learner4.train_observed"
    },
    {
      "id": "6709a16cc85f062399d3c4c5",
      "name": "learner4.games_played"
    },
    {
      "id": "6709a16cc85f062399d3c4c7",
      "name": "learner4.games_won"
    },
    {
      "id": "6709a16cc85f062399d3c4c9",
      "name": "learner4.games_lost"
    },
    {
      "id": "6709a16cc85f062399d3c4cb",
      "name": "learner4.games_tie"
    },
    {
      "id": "6709a16cc85f062399d3c4cd",
      "name": "learner4.rating"
    },
    {
      "id": "6709a16cc85f062399d3c4cf",
      "name": "learner3.train_correct"
    },
    {
      "id": "6709a16cc85f062399d3c4d1",
      "name": "learner3.train_observed"
    },
    {
      "id": "6709a16cc85f062399d3c4d3",
      "name": "learner3.games_played"
    },
    {
      "id": "6709a16cc85f062399d3c4d5",
      "name": "learner3.games_won"
    },
    {
      "id": "6709a16cc85f062399d3c4d7",
      "name": "learner3.games_lost"
    },
    {
      "id": "6709a16cc85f062399d3c4d9",
      "name": "learner3.games_tie"
    },
    {
      "id": "6709a16cc85f062399d3c4db",
      "name": "learner3.rating"
    },
    {
      "id": "6709a16cc85f062399d3c4dd",
      "name": "learner0.train_correct"
    },
    {
      "id": "6709a16dc85f062399d3c4df",
      "name": "learner0.train_observed"
    },
    {
      "id": "6709a16dc85f062399d3c4e1",
      "name": "learner0.games_played"
    },
    {
      "id": "6709a16dc85f062399d3c4e3",
      "name": "learner0.games_won"
    },
    {
      "id": "6709a16dc85f062399d3c4e5",
      "name": "learner0.games_lost"
    },
    {
      "id": "6709a16dc85f062399d3c4e7",
      "name": "learner0.games_tie"
    },
    {
      "id": "6709a16dc85f062399d3c4e9",
      "name": "learner0.rating"
    },
    {
      "id": "6709a16dc85f062399d3c4eb",
      "name": "learner5.train_correct"
    },
    {
      "id": "6709a16dc85f062399d3c4ed",
      "name": "learner5.train_observed"
    },
    {
      "id": "6709a16dc85f062399d3c4ef",
      "name": "learner5.games_played"
    },
    {
      "id": "6709a16dc85f062399d3c4f1",
      "name": "learner5.games_won"
    },
    {
      "id": "6709a16dc85f062399d3c4f3",
      "name": "learner5.games_lost"
    },
    {
      "id": "6709a16dc85f062399d3c4f5",
      "name": "learner5.games_tie"
    },
    {
      "id": "6709a16dc85f062399d3c4f7",
      "name": "learner5.rating"
    },
    {
      "id": "6709a16dc85f062399d3c4f9",
      "name": "learner0.test_accuracy"
    },
    {
      "id": "6709a16dc85f062399d3c4fb",
      "name": "learner0.relative_rating"
    },
    {
      "id": "6709a16dc85f062399d3c4fd",
      "name": "learner1.test_accuracy"
    },
    {
      "id": "6709a16dc85f062399d3c4ff",
      "name": "learner1.relative_rating"
    },
    {
      "id": "6709a16dc85f062399d3c501",
      "name": "learner2.test_accuracy"
    },
    {
      "id": "6709a16dc85f062399d3c503",
      "name": "learner2.relative_rating"
    },
    {
      "id": "6709a16dc85f062399d3c505",
      "name": "learner3.test_accuracy"
    },
    {
      "id": "6709a16dc85f062399d3c509",
      "name": "learner3.relative_rating"
    },
    {
      "id": "6709a16dc85f062399d3c50d",
      "name": "learner4.test_accuracy"
    },
    {
      "id": "6709a16dc85f062399d3c50f",
      "name": "learner4.relative_rating"
    },
    {
      "id": "6709a16dc85f062399d3c511",
      "name": "learner5.test_accuracy"
    },
    {
      "id": "6709a16dc85f062399d3c513",
      "name": "learner5.relative_rating"
    },
    {
      "id": "6709a16dc85f062399d3c515",
      "name": "ensemble.best_rated_accuracy"
    },
    {
      "id": "6709a16dc85f062399d3c517",
      "name": "ensemble.majority_accuracy"
    }
  ]
}