{
  "metrics": [
    {
      "id": "6705aefada2a8267af0d58bf",
      "name": "learner5.train_correct"
    },
    {
      "id": "6705aefada2a8267af0d58c1",
      "name": "learner5.train_observed"
    },
    {
      "id": "6705aefada2a8267af0d58c3",
      "name": "learner5.games_played"
    },
    {
      "id": "6705aefada2a8267af0d58c5",
      "name": "learner5.games_won"
    },
    {
      "id": "6705aefada2a8267af0d58c7",
      "name": "learner5.games_lost"
    },
    {
      "id": "6705aefada2a8267af0d58c9",
      "name": "learner5.games_tie"
    },
    {
      "id": "6705aefada2a8267af0d58cb",
      "name": "learner3.train_correct"
    },
    {
      "id": "6705aefada2a8267af0d58cd",
      "name": "learner3.train_observed"
    },
    {
      "id": "6705aefada2a8267af0d58cf",
      "name": "learner3.games_played"
    },
    {
      "id": "6705aefada2a8267af0d58d1",
      "name": "learner3.games_won"
    },
    {
      "id": "6705aefada2a8267af0d58d3",
      "name": "learner3.games_lost"
    },
    {
      "id": "6705aefada2a8267af0d58d5",
      "name": "learner3.games_tie"
    },
    {
      "id": "6705aefada2a8267af0d58d7",
      "name": "learner1.train_correct"
    },
    {
      "id": "6705aefada2a8267af0d58d9",
      "name": "learner1.train_observed"
    },
    {
      "id": "6705aefada2a8267af0d58db",
      "name": "learner1.games_played"
    },
    {
      "id": "6705aefada2a8267af0d58dd",
      "name": "learner1.games_won"
    },
    {
      "id": "6705aefada2a8267af0d58df",
      "name": "learner1.games_lost"
    },
    {
      "id": "6705aefada2a8267af0d58e1",
      "name": "learner1.games_tie"
    },
    {
      "id": "6705aefada2a8267af0d58e3",
      "name": "learner2.train_correct"
    },
    {
      "id": "6705aefada2a8267af0d58e5",
      "name": "learner2.train_observed"
    },
    {
      "id": "6705aefada2a8267af0d58e7",
      "name": "learner2.games_played"
    },
    {
      "id": "6705aefada2a8267af0d58e9",
      "name": "learner2.games_won"
    },
    {
      "id": "6705aefada2a8267af0d58eb",
      "name": "learner2.games_lost"
    },
    {
      "id": "6705aefada2a8267af0d58ed",
      "name": "learner2.games_tie"
    },
    {
      "id": "6705aefada2a8267af0d58ef",
      "name": "learner0.train_correct"
    },
    {
      "id": "6705aefada2a8267af0d58f1",
      "name": "learner0.train_observed"
    },
    {
      "id": "6705aefada2a8267af0d58f3",
      "name": "learner0.games_played"
    },
    {
      "id": "6705aefada2a8267af0d58f5",
      "name": "learner0.games_won"
    },
    {
      "id": "6705aefada2a8267af0d58f7",
      "name": "learner0.games_lost"
    },
    {
      "id": "6705aefada2a8267af0d58f9",
      "name": "learner0.games_tie"
    },
    {
      "id": "6705aefbda2a8267af0d58fb",
      "name": "learner4.train_correct"
    },
    {
      "id": "6705aefbda2a8267af0d58fd",
      "name": "learner4.train_observed"
    },
    {
      "id": "6705aefbda2a8267af0d58ff",
      "name": "learner4.games_played"
    },
    {
      "id": "6705aefbda2a8267af0d5901",
      "name": "learner4.games_won"
    },
    {
      "id": "6705aefbda2a8267af0d5903",
      "name": "learner4.games_lost"
    },
    {
      "id": "6705aefbda2a8267af0d5905",
      "name": "learner4.games_tie"
    },
    {
      "id": "6705aefbda2a8267af0d5907",
      "name": "learner0.test_accuracy"
    },
    {
      "id": "6705aefbda2a8267af0d5909",
      "name": "learner1.test_accuracy"
    },
    {
      "id": "6705aefbda2a8267af0d590b",
      "name": "learner2.test_accuracy"
    },
    {
      "id": "6705aefbda2a8267af0d590d",
      "name": "learner3.test_accuracy"
    },
    {
      "id": "6705aefbda2a8267af0d590f",
      "name": "learner4.test_accuracy"
    },
    {
      "id": "6705aefbda2a8267af0d5911",
      "name": "learner5.test_accuracy"
    },
    {
      "id": "6705aefbda2a8267af0d5913",
      "name": "ensemble.majority_accuracy"
    }
  ]
}